aula_(09)_may/lab6/register_file.v
module register_file #(
    parameter DATA_WIDTH = 32, // 32-bits de dados
    parameter ADDR_WIDTH = 5,  // 5-bits de endereço (até 32 registros)
    parameter REG_COUNT  = 32  // 32 registros
)(
    input  wire                     clk,
    input  wire                     wr_en,
    input  wire [ADDR_WIDTH-1:0]    wr_addr,
    input  wire [DATA_WIDTH-1:0]    wr_data,
    input  wire [ADDR_WIDTH-1:0]    rd_addr1,
    input  wire [ADDR_WIDTH-1:0]    rd_addr2,
    output wire [DATA_WIDTH-1:0]    rd_data1,
    output wire [DATA_WIDTH-1:0]    rd_data2,
    output reg                      wr_ack
);

    // Memória RAM implementando o banco de registradores
    reg [DATA_WIDTH-1:0] registers [0:REG_COUNT-1];

    // Escrita síncrona
    always @(posedge clk) begin
        if (wr_en) begin
            if(wr_addr != 0) begin 
                registers[wr_addr] <= wr_data;
            end
        end
    end

    // Leitura combinacional (assíncrona)
    assign rd_data1 = rd_addr1 == 0 ? {DATA_WIDTH{1'b0}} : registers[rd_addr1];
    assign rd_data2 = rd_addr2 == 0 ? {DATA_WIDTH{1'b0}} : registers[rd_addr2];

endmodule

aula_(09)_may/lab6/tb_register_file.v
`timescale 1ns/1ps

module tb_register_file;

    // Parâmetros
    parameter DATA_WIDTH = 16;
    parameter ADDR_WIDTH = 3;
    parameter REG_COUNT  = 8;

    // Sinais do DUT
    reg                         clk;
    reg                         wr_en;
    reg  [ADDR_WIDTH-1:0]      wr_addr;
    reg  [DATA_WIDTH-1:0]      wr_data;
    reg  [ADDR_WIDTH-1:0]      rd_addr1;
    reg  [ADDR_WIDTH-1:0]      rd_addr2;

    wire [DATA_WIDTH-1:0]      rd_data1;
    wire [DATA_WIDTH-1:0]      rd_data2;

    // Instanciação do DUT
    register_file #(
        .DATA_WIDTH(DATA_WIDTH),
        .ADDR_WIDTH(ADDR_WIDTH),
        .REG_COUNT(REG_COUNT)
    ) dut (
        .clk(clk),
        .wr_en(wr_en),
        .wr_addr(wr_addr),
        .wr_data(wr_data),
        .rd_addr1(rd_addr1),
        .rd_addr2(rd_addr2),
        .rd_data1(rd_data1),
        .rd_data2(rd_data2)
    );

    // Clock de 10ns
    initial begin
        clk = 0;
        forever #5 clk = ~clk;
    end

    initial begin
        $dumpfile("wave.vcd");
        $dumpvars(0, tb_register_file);
    end

    // Procedimento de teste
    initial begin

        // Inicialização
        wr_en    = 0;
        wr_addr  = 0;
        wr_data  = 0;
        rd_addr1 = 0;
        rd_addr2 = 0;

        // Aguarda alguns ciclos
        #20;

        $display("======================================");
        $display("TESTE 1 - Escrita no registrador x1");
        $display("======================================");

        // Escreve no registrador 1
        @(posedge clk);
        wr_en   <= 1;
        wr_addr <= 3'd1;
        wr_data <= 16'hAABB;

        @(posedge clk);
        wr_en <= 0;

        // Leitura
        rd_addr1 <= 3'd1;

        #2;

        $display("Registrador x1 = %h", rd_data1);

        if (rd_data1 == 16'hAABB)
            $display("TESTE 1 PASSOU\n");
        else
            $display("TESTE 1 FALHOU\n");

        // ------------------------------------------------

        $display("======================================");
        $display("TESTE 2 - Escrita no registrador x5");
        $display("======================================");

        @(posedge clk);
        wr_en   <= 1;
        wr_addr <= 3'd5;
        wr_data <= 16'h1234;

        @(posedge clk);
        wr_en <= 0;

        rd_addr1 <= 3'd5;

        #2;

        $display("Registrador x5 = %h", rd_data1);

        if (rd_data1 == 16'h1234)
            $display("TESTE 2 PASSOU\n");
        else
            $display("TESTE 2 FALHOU\n");

        // ------------------------------------------------

        $display("======================================");
        $display("TESTE 3 - Registrador x0 deve ser zero");
        $display("======================================");

        // Tentativa de escrita em x0
        @(posedge clk);
        wr_en   <= 1;
        wr_addr <= 3'd0;
        wr_data <= 16'hFFFF;

        @(posedge clk);
        wr_en <= 0;

        rd_addr1 <= 3'd0;

        #2;

        $display("Registrador x0 = %h", rd_data1);

        if (rd_data1 == 16'h0000)
            $display("TESTE 3 PASSOU\n");
        else
            $display("TESTE 3 FALHOU\n");

        // ------------------------------------------------

        $display("======================================");
        $display("TESTE 4 - Leitura simultânea");
        $display("======================================");

        rd_addr1 <= 3'd1;
        rd_addr2 <= 3'd5;

        #2;

        $display("rd_data1 (x1) = %h", rd_data1);
        $display("rd_data2 (x5) = %h", rd_data2);

        if ((rd_data1 == 16'hAABB) &&
            (rd_data2 == 16'h1234))
            $display("TESTE 4 PASSOU\n");
        else
            $display("TESTE 4 FALHOU\n");

        // ------------------------------------------------

        $display("======================================");
        $display("FIM DA SIMULACAO");
        $display("======================================");

        #20;
        $finish;
    end

endmodule

aula_(09)_may/lab6/wave.vcd
$date
	Sun May 10 21:36:32 2026
$end
$version
	Icarus Verilog
$end
$timescale
	1ps
$end
$scope module tb_register_file $end
$var wire 16 ! rd_data2 [15:0] $end
$var wire 16 " rd_data1 [15:0] $end
$var parameter 32 # ADDR_WIDTH $end
$var parameter 32 $ DATA_WIDTH $end
$var parameter 32 % REG_COUNT $end
$var reg 1 & clk $end
$var reg 3 ' rd_addr1 [2:0] $end
$var reg 3 ( rd_addr2 [2:0] $end
$var reg 3 ) wr_addr [2:0] $end
$var reg 16 * wr_data [15:0] $end
$var reg 1 + wr_en $end
$scope module dut $end
$var wire 1 & clk $end
$var wire 3 , rd_addr1 [2:0] $end
$var wire 3 - rd_addr2 [2:0] $end
$var wire 3 . wr_addr [2:0] $end
$var wire 16 / wr_data [15:0] $end
$var wire 1 + wr_en $end
$var wire 16 0 rd_data2 [15:0] $end
$var wire 16 1 rd_data1 [15:0] $end
$var parameter 32 2 ADDR_WIDTH $end
$var parameter 32 3 DATA_WIDTH $end
$var parameter 32 4 REG_COUNT $end
$var reg 1 5 wr_ack $end
$upscope $end
$upscope $end
$enddefinitions $end
$comment Show the parameter values. $end
$dumpall
b1000 4
b10000 3
b11 2
b1000 %
b10000 $
b11 #
$end
#0
$dumpvars
x5
b0 1
b0 0
b0 /
b0 .
b0 -
b0 ,
0+
b0 *
b0 )
b0 (
b0 '
0&
b0 "
b0 !
$end
#5000
1&
#10000
0&
#15000
1&
#20000
0&
#25000
b1010101010111011 *
b1010101010111011 /
b1 )
b1 .
1+
1&
#30000
0&
#35000
b1010101010111011 "
b1010101010111011 1
b1 '
b1 ,
0+
1&
#40000
0&
#45000
b1001000110100 *
b1001000110100 /
b101 )
b101 .
1+
1&
#50000
0&
#55000
b1001000110100 "
b1001000110100 1
b101 '
b101 ,
0+
1&
#60000
0&
#65000
b1111111111111111 *
b1111111111111111 /
b0 )
b0 .
1+
1&
#70000
0&
#75000
b0 "
b0 1
b0 '
b0 ,
0+
1&
#77000
b1001000110100 !
b1001000110100 0
b1010101010111011 "
b1010101010111011 1
b101 (
b101 -
b1 '
b1 ,
