aula_(09)_may/lab1/ram_dual.v
module ram_dual (
    input  wire        clk,
    input  wire        we_a,
    input  wire        cs,
    input  wire [5:0]  addr_wr_a,
    input  wire [7:0]  data_wr_a,
    input  wire [5:0]  addr_rd_b,
    output reg  [7:0]  data_rd_a,
    output reg  [7:0]  data_rd_b
);

    reg [7:0] ram [0:63];

    always @(posedge clk) begin
        if(cs) begin 
            if (we_a) begin
                ram[addr_wr_a] <= data_wr_a;
            end else begin 
                data_rd_a <= ram[addr_wr_a];
            end

            data_rd_b <= ram[addr_rd_b];
        end
    end

endmodule

aula_(09)_may/lab1/ram_single.v
module ram_single (
    input  wire         clk,
    input  wire         cs,
    input  wire         we,
    input  wire [4:0]   addr,
    input  wire [15:0]  data_in,
    output reg  [15:0]  data_out
);

    reg [15:0] ram [0:31];

    always @(posedge clk) begin
        if(cs) begin 
            if (we) begin
                ram[addr] <= data_in;
                data_out  <= data_in;
            end

            else begin
                data_out <= ram[addr];
            end
        end
    end

endmodule

aula_(09)_may/lab1/rom.v
module rom (
    input  wire        clk,
    input  wire [3:0]  addr,
    output reg  [7:0]  data_out
);

    reg [7:0] rom [0:15];

    initial begin
        rom[0]  = 8'd0;
        rom[1]  = 8'd1;
        rom[2]  = 8'd1;
        rom[3]  = 8'd2;
        rom[4]  = 8'd3;
        rom[5]  = 8'd5;
        rom[6]  = 8'd8;
        rom[7]  = 8'd13;
        rom[8]  = 8'd21;
        rom[9]  = 8'd34;
        rom[10] = 8'd55;
        rom[11] = 8'd89;
        rom[12] = 8'd144;
        rom[13] = 8'd233;
        rom[14] = 8'd121;
        rom[15] = 8'd98; 
    end

    always @(posedge clk) begin
        data_out <= rom[addr];
    end

endmodule

aula_(09)_may/lab1/memory_tb.v
`timescale 1ns/1ps

module memory_tb;

    reg clk;
    reg cs = 1;
    

    initial begin
        clk = 0;
        forever #5 clk = ~clk;
    end

    reg  [3:0] rom_addr;
    wire [7:0] rom_data_out;

    rom ROM (
        .clk(clk),
        .addr(rom_addr),
        .data_out(rom_data_out)
    );

    reg         sp_we;
    reg  [4:0]  sp_addr;
    reg  [15:0] sp_data_in;
    wire [15:0] sp_data_out;

    ram_single RAM_SP (
        .clk(clk),
        .cs(cs),
        .we(sp_we),
        .addr(sp_addr),
        .data_in(sp_data_in),
        .data_out(sp_data_out)
    );

    reg        dp_we;
    reg [5:0]  dp_addr_wr;
    reg [7:0]  dp_data_wr;

    reg [5:0]  dp_addr_rd;
    wire [7:0] dp_data_rd;
    wire [7:0] dp_data_rd_a;

    ram_dual RAM_DP (
        .clk(clk),
        .cs(cs),
        
        .we_a(dp_we),
        .addr_wr_a(dp_addr_wr),
        .data_wr_a(dp_data_wr),
        .data_rd_a(dp_data_rd_a),
        .addr_rd_b(dp_addr_rd),
        .data_rd_b(dp_data_rd)
    );

    // =====================================================
    // TESTES
    // =====================================================

    initial begin

        $display("\n========================================");
        $display("INICIO DA SIMULACAO");
        $display("========================================");

        // Inicialização geral
        rom_addr      = 0;

        sp_we         = 0;
        sp_addr       = 0;
        sp_data_in    = 0;

        dp_we       = 0;
        dp_addr_wr     = 0;
        dp_data_wr  = 0;
        dp_addr_rd     = 0;

        // Aguarda alguns ciclos
        #10;

        $display("\n========================================");
        $display("TESTE ROM 16x8");
        $display("========================================");

        rom_addr = 4'd0;
        #10;

        rom_addr = 4'd1;
        #10;

        rom_addr = 4'd5;
        #10;

        rom_addr = 4'd10;
        #10;

        rom_addr = 4'd15;
        #10;

        $display("\n========================================");
        $display("TESTE RAM SINGLE PORT 32x16");
        $display("========================================");

        // Escrita endereço 3
        sp_we      = 1;
        sp_addr    = 5'd3;
        sp_data_in = 16'd100;
        #10;

        // Escrita endereço 7
        sp_addr    = 5'd7;
        sp_data_in = 16'd200;
        #10;

        // Escrita endereço 10
        sp_addr    = 5'd10;
        sp_data_in = 16'd300;
        #10;

        // Desabilita escrita
        sp_we = 0;

        // Leitura endereço 3
        sp_addr = 5'd3;
        #10;

        // Leitura endereço 7
        sp_addr = 5'd7;
        #10;

        // Leitura endereço 10
        sp_addr = 5'd10;
        #10;

        // Persistência
        sp_addr = 5'd3;
        #10;

        $display("\n========================================");
        $display("TESTE RAM DUAL PORT 64x8");
        $display("========================================");

        // Escrita endereço 4
        dp_we      = 1;
        dp_addr_wr    = 6'd4;
        dp_data_wr = 8'd50;
        #10;

        // Escrita endereço 8
        dp_addr_wr    = 6'd8;
        dp_data_wr = 8'd100;
        #10;

        // Escrita endereço 12
        dp_addr_wr    = 6'd12;
        dp_data_wr = 8'd150;
        #10;

        // Finaliza escrita
        dp_we = 0;

        // Leitura endereço 4
        dp_addr_rd = 6'd4;
        #10;

        // Leitura endereço 8
        dp_addr_rd = 6'd8;
        #10;

        // Leitura endereço 12
        dp_addr_rd = 6'd12;
        #10;

        // Escrita e leitura simultânea
        dp_we      = 1;
        dp_addr_wr    = 6'd20;
        dp_data_wr = 8'd77;

        dp_addr_rd    = 6'd8;
        #10;

        // Leitura do novo valor
        dp_we   = 0;
        dp_addr_rd = 6'd20;
        #10;

        $display("\n========================================");
        $display("FIM DA SIMULACAO");
        $display("========================================");

        #20;
        $finish;

    end

    initial begin
        $monitor(
            "\nTempo=%0t\nROM -> addr=%d data=%d\nSP_RAM -> we=%b addr=%d in=%d out=%d\nDP_RAM -> we=%b addrA=%d inA=%d addrB=%d outB=%d\n",
            $time,

            rom_addr,
            rom_data_out,

            sp_we,
            sp_addr,
            sp_data_in,
            sp_data_out,

            dp_we,
            dp_addr_wr,
            dp_data_wr,
            dp_addr_rd,
            dp_data_rd
        );
    end

    initial begin
        $dumpfile("wave.vcd");
        $dumpvars(0, memory_tb);
    end

endmodule

aula_(09)_may/lab1/wave.vcd
$date
	Sat May  9 19:01:03 2026
$end
$version
	Icarus Verilog
$end
$timescale
	1ps
$end
$scope module memory_tb $end
$var wire 16 ! sp_data_out [15:0] $end
$var wire 8 " rom_data_out [7:0] $end
$var wire 8 # dp_data_rd_a [7:0] $end
$var wire 8 $ dp_data_rd [7:0] $end
$var reg 1 % clk $end
$var reg 1 & cs $end
$var reg 6 ' dp_addr_rd [5:0] $end
$var reg 6 ( dp_addr_wr [5:0] $end
$var reg 8 ) dp_data_wr [7:0] $end
$var reg 1 * dp_we $end
$var reg 4 + rom_addr [3:0] $end
$var reg 5 , sp_addr [4:0] $end
$var reg 16 - sp_data_in [15:0] $end
$var reg 1 . sp_we $end
$scope module RAM_DP $end
$var wire 6 / addr_rd_b [5:0] $end
$var wire 6 0 addr_wr_a [5:0] $end
$var wire 1 % clk $end
$var wire 1 & cs $end
$var wire 8 1 data_wr_a [7:0] $end
$var wire 1 * we_a $end
$var reg 8 2 data_rd_a [7:0] $end
$var reg 8 3 data_rd_b [7:0] $end
$upscope $end
$scope module RAM_SP $end
$var wire 5 4 addr [4:0] $end
$var wire 1 % clk $end
$var wire 1 & cs $end
$var wire 16 5 data_in [15:0] $end
$var wire 1 . we $end
$var reg 16 6 data_out [15:0] $end
$upscope $end
$scope module ROM $end
$var wire 4 7 addr [3:0] $end
$var wire 1 % clk $end
$var reg 8 8 data_out [7:0] $end
$upscope $end
$upscope $end
$enddefinitions $end
$comment Show the parameter values. $end
$dumpall
$end
#0
$dumpvars
bx 8
b0 7
bx 6
b0 5
b0 4
bx 3
bx 2
b0 1
b0 0
b0 /
0.
b0 -
b0 ,
b0 +
0*
b0 )
b0 (
b0 '
1&
0%
bx $
bx #
bx "
bx !
$end
#5000
b0 "
b0 8
1%
#10000
0%
#15000
1%
#20000
0%
b1 +
b1 7
#25000
b1 "
b1 8
1%
#30000
0%
b101 +
b101 7
#35000
b101 "
b101 8
1%
#40000
0%
b1010 +
b1010 7
#45000
b110111 "
b110111 8
1%
#50000
0%
b1111 +
b1111 7
#55000
b1100010 "
b1100010 8
1%
#60000
0%
b1100100 -
b1100100 5
b11 ,
b11 4
1.
#65000
b1100100 !
b1100100 6
1%
#70000
0%
b11001000 -
b11001000 5
b111 ,
b111 4
#75000
b11001000 !
b11001000 6
1%
#80000
0%
b100101100 -
b100101100 5
b1010 ,
b1010 4
#85000
b100101100 !
b100101100 6
1%
#90000
0%
b11 ,
b11 4
0.
#95000
b1100100 !
b1100100 6
1%
#100000
0%
b111 ,
b111 4
#105000
b11001000 !
b11001000 6
1%
#110000
0%
b1010 ,
b1010 4
#115000
b100101100 !
b100101100 6
1%
#120000
0%
b11 ,
b11 4
#125000
b1100100 !
b1100100 6
1%
#130000
0%
b110010 )
b110010 1
b100 (
b100 0
1*
#135000
1%
#140000
0%
b1100100 )
b1100100 1
b1000 (
b1000 0
#145000
1%
#150000
0%
b10010110 )
b10010110 1
b1100 (
b1100 0
#155000
1%
#160000
0%
b100 '
b100 /
0*
#165000
b110010 $
b110010 3
b10010110 #
b10010110 2
1%
#170000
0%
b1000 '
b1000 /
#175000
b1100100 $
b1100100 3
1%
#180000
0%
b1100 '
b1100 /
#185000
b10010110 $
b10010110 3
1%
#190000
0%
b1000 '
b1000 /
b1001101 )
b1001101 1
b10100 (
b10100 0
1*
#195000
b1100100 $
b1100100 3
1%
#200000
0%
b10100 '
b10100 /
0*
#205000
b1001101 $
b1001101 3
b1001101 #
b1001101 2
1%
