aula_(11_12)_april/lab5/counter.v
module counter
#(
    parameter COUNTER_WIDTH = 16
)
(
    input  wire clk, 
    input  wire a_rst,
    input  wire enable,
    input  wire load,
    input  wire mode,
    input  wire [COUNTER_WIDTH-1:0] data_in, 
    output reg  [COUNTER_WIDTH-1:0] counter_o 
);

always @(posedge clk or posedge a_rst) begin
    if (a_rst) begin
        counter_o <= {COUNTER_WIDTH{1'b0}};
    end else begin
        if (load) begin
            counter_o <= data_in;
        end else if (enable) begin
            counter_o <= mode ? counter_o + 1 : counter_o - 1;
        end
    end
end

endmodule

aula_(11_12)_april/lab5/counter_tb.v
`timescale 1ns/1ps

module counter_tb;

parameter COUNTER_WIDTH = 16;

reg clk;
reg a_rst;
reg enable;
reg load;
reg mode;
reg [COUNTER_WIDTH-1:0] data_in;
wire [COUNTER_WIDTH-1:0] counter_o;

counter #(
    .COUNTER_WIDTH(COUNTER_WIDTH)
) uut (
    .clk(clk),
    .a_rst(a_rst),
    .enable(enable),
    .load(load),
    .mode(mode),
    .data_in(data_in),
    .counter_o(counter_o)
);

always #5 clk = ~clk;

initial begin
    $dumpfile("counter.vcd");
    $dumpvars(0, counter_tb);

    // init
    clk = 0;
    a_rst = 1;
    enable = 0;
    load = 0;
    mode = 0;
    data_in = 0;

    // reset
    #10;
    a_rst = 0;

    // load valor inicial
    #10;
    load = 1;
    data_in = 16'd10;
    #10;
    load = 0;

    // contagem crescente
    enable = 1;
    mode = 1;
    #50;

    // contagem decrescente
    mode = 0;
    #50;

    // desabilita contador
    enable = 0;
    #20;

    // novo load
    load = 1;
    data_in = 16'd100;
    #10;
    load = 0;

    // conta de novo
    enable = 1;
    mode = 1;
    #50;

    $finish;
end

endmodule

aula_(11_12)_april/lab5/counter.vcd
$date
	Sun Apr 12 10:05:07 2026
$end
$version
	Icarus Verilog
$end
$timescale
	1ps
$end
$scope module counter_tb $end
$var wire 16 ! counter_o [15:0] $end
$var parameter 32 " COUNTER_WIDTH $end
$var reg 1 # a_rst $end
$var reg 1 $ clk $end
$var reg 16 % data_in [15:0] $end
$var reg 1 & enable $end
$var reg 1 ' load $end
$var reg 1 ( mode $end
$scope module uut $end
$var wire 1 # a_rst $end
$var wire 1 $ clk $end
$var wire 16 ) data_in [15:0] $end
$var wire 1 & enable $end
$var wire 1 ' load $end
$var wire 1 ( mode $end
$var parameter 32 * COUNTER_WIDTH $end
$var reg 16 + counter_o [15:0] $end
$upscope $end
$upscope $end
$enddefinitions $end
$comment Show the parameter values. $end
$dumpall
b10000 *
b10000 "
$end
#0
$dumpvars
b0 +
b0 )
0(
0'
0&
b0 %
0$
1#
b0 !
$end
#5000
1$
#10000
0$
0#
#15000
1$
#20000
0$
b1010 %
b1010 )
1'
#25000
b1010 !
b1010 +
1$
#30000
0$
1(
1&
0'
#35000
b1011 !
b1011 +
1$
#40000
0$
#45000
b1100 !
b1100 +
1$
#50000
0$
#55000
b1101 !
b1101 +
1$
#60000
0$
#65000
b1110 !
b1110 +
1$
#70000
0$
#75000
b1111 !
b1111 +
1$
#80000
0$
0(
#85000
b1110 !
b1110 +
1$
#90000
0$
#95000
b1101 !
b1101 +
1$
#100000
0$
#105000
b1100 !
b1100 +
1$
#110000
0$
#115000
b1011 !
b1011 +
1$
#120000
0$
#125000
b1010 !
b1010 +
1$
#130000
0$
0&
#135000
1$
#140000
0$
#145000
1$
#150000
0$
b1100100 %
b1100100 )
1'
#155000
b1100100 !
b1100100 +
1$
#160000
0$
1(
1&
0'
#165000
b1100101 !
b1100101 +
1$
#170000
0$
#175000
b1100110 !
b1100110 +
1$
#180000
0$
#185000
b1100111 !
b1100111 +
1$
#190000
0$
#195000
b1101000 !
b1101000 +
1$
#200000
0$
#205000
b1101001 !
b1101001 +
1$
