aula_(09)_may/lab8/single_port_ram.v
module single_port_ram(
 input wire     clk,
 input wire     we,
 input wire     cs,
 input wire [9:0] addr,
 input wire [7:0] din,
 output wire [7:0] dout
 );

 reg [7:0] mem [0:1023];
 reg [7:0] saida;

 assign dout = saida;

 integer i;

 initial begin
    saida = 8'd0;

    for(i = 0; i < 1024; i = i + 1) begin
        mem[i] = 8'd0;
    end

 end


 always @(posedge clk) begin
    if (cs) begin
        if (we) begin 
            mem[addr] <= din;
        end
        saida <= mem[addr];
    end
 end

endmodule

aula_(09)_may/lab8/decoder_ram_4x1.v
module decoder_ram_4x1 (
    input wire [15:0] addr,
    output wire [9:0] effective_addr,
    output wire cs0,
    output wire cs1,
    output wire cs2,
    output wire cs3

);

assign effective_addr = addr[9:0];
assign cs0 = (addr >= 16'h0400 && addr <= 16'h07FF);
assign cs1 = (addr >= 16'h0800 && addr <= 16'h0BFF);
assign cs2 = (addr >= 16'h0C00 && addr <= 16'h0FFF);
assign cs3 = (addr >= 16'h1000 && addr <= 16'h13FF);



endmodule

aula_(09)_may/lab8/tb_decoder_ram_4x1.v
`timescale 1ns/1ps

module tb_decoder_ram_4x1;
reg clk;
reg we;
reg [15:0] addr;
reg [7:0] din;
wire [7:0] dout0;
wire [7:0] dout1;
wire [7:0] dout2;
wire [7:0] dout3;
wire [9:0] effective_addr;

wire cs0, cs1, cs2, cs3;

decoder_ram_4x1 dut (
    .addr(addr),
    .effective_addr(effective_addr),
    .cs0(cs0),
    .cs1(cs1),
    .cs2(cs2),
    .cs3(cs3)

);

// ======================================================
// MEMORIAS
// ======================================================

single_port_ram ram0 (
    .clk(clk),
    .we(we),
    .cs(cs0),
    .addr(effective_addr),
    .din(din),
    .dout(dout0)
);

single_port_ram ram1 (
    .clk(clk),
    .we(we),
    .cs(cs1),
    .addr(effective_addr),
    .din(din),
    .dout(dout1)
);

single_port_ram ram2 (
    .clk(clk),
    .we(we),
    .cs(cs2),
    .addr(effective_addr),
    .din(din),
    .dout(dout2)
);

single_port_ram ram3 (
    .clk(clk),
    .we(we),
    .cs(cs3),
    .addr(effective_addr),
    .din(din),
    .dout(dout3)
);

always #5 clk = ~clk;

initial begin

    $dumpfile("wave.vcd");
    $dumpvars(0, tb_decoder_ram_4x1);

    clk  = 0;
    we   = 0;
    addr = 0;
    din  = 0;

    $display("\n====================================");
    $display(" TESTBENCH DECODER RAM 4x1 ");
    $display("====================================\n");

    // =================================================
    // TESTE 1 - ESCRITA
    // =================================================

    $display(">>> TESTE 1 - ESCRITA");

    we = 1;

    addr = 16'h0402;
    din  = 8'hA5;
    #10;
    $display("WRITE RAM0 | ADDR=0x%h | DATA=0x%h | CS=%b%b%b%b",
              addr, din, cs3, cs2, cs1, cs0);

    addr = 16'h0810;
    din  = 8'hB6;
    #10;
    $display("WRITE RAM1 | ADDR=0x%h | DATA=0x%h | CS=%b%b%b%b",
              addr, din, cs3, cs2, cs1, cs0);

    addr = 16'h0C20;
    din  = 8'hC7;
    #10;
    $display("WRITE RAM2 | ADDR=0x%h | DATA=0x%h | CS=%b%b%b%b",
              addr, din, cs3, cs2, cs1, cs0);

    addr = 16'h1015;
    din  = 8'hD8;
    #10;
    $display("WRITE RAM3 | ADDR=0x%h | DATA=0x%h | CS=%b%b%b%b",
              addr, din, cs3, cs2, cs1, cs0);

    // =================================================
    // TESTE 2 - LEITURA
    // =================================================

    $display("\n>>> TESTE 2 - LEITURA");

    we = 0;

    addr = 16'h0402;
    #10;
    $display("READ RAM0  | ESPERADO=0xA5 | RECEBIDO=0x%h",
              dout0);

    addr = 16'h0810;
    #10;
    $display("READ RAM1  | ESPERADO=0xB6 | RECEBIDO=0x%h",
              dout1);

    addr = 16'h0C20;
    #10;
    $display("READ RAM2  | ESPERADO=0xC7 | RECEBIDO=0x%h",
              dout2);

    addr = 16'h1015;
    #10;
    $display("READ RAM3  | ESPERADO=0xD8 | RECEBIDO=0x%h",
              dout3);

    // =================================================
    // TESTE 3 - SOBRESCRITA
    // =================================================

    $display("\n>>> TESTE 3 - SOBRESCRITA");

    we = 1;

    addr = 16'h0402;
    din  = 8'h55;
    #10;

    addr = 16'h0402;
    din  = 8'h99;
    #10;

    we = 0;

    addr = 16'h0402;
    #10;

    $display("READ RAM0  | ESPERADO=0x99 | RECEBIDO=0x%h",
              dout0);

    // =================================================
    // TESTE 4 - MULTIPLOS ENDERECOS
    // =================================================

    $display("\n>>> TESTE 4 - MULTIPLOS ENDERECOS");

    we = 1;

    addr = 16'h0800; din = 8'h11; #10;
    addr = 16'h0801; din = 8'h22; #10;
    addr = 16'h0802; din = 8'h33; #10;
    addr = 16'h0803; din = 8'h44; #10;

    we = 0;

    addr = 16'h0800; #10;
    $display("ADDR=0x0800 | ESP=0x11 | REC=0x%h", dout1);

    addr = 16'h0801; #10;
    $display("ADDR=0x0801 | ESP=0x22 | REC=0x%h", dout1);

    addr = 16'h0802; #10;
    $display("ADDR=0x0802 | ESP=0x33 | REC=0x%h", dout1);

    addr = 16'h0803; #10;
    $display("ADDR=0x0803 | ESP=0x44 | REC=0x%h", dout1);

    // =================================================
    // TESTE 5 - ENDERECOS INVALIDOS
    // =================================================

    $display("\n>>> TESTE 5 - ENDERECOS INVALIDOS");

    addr = 16'h0000;
    #10;

    $display("ADDR=0x0000 | CS0=%b CS1=%b CS2=%b CS3=%b",
              cs0, cs1, cs2, cs3);

    addr = 16'hFFFF;
    #10;

    $display("ADDR=0xFFFF | CS0=%b CS1=%b CS2=%b CS3=%b",
              cs0, cs1, cs2, cs3);

    // =================================================
    // FINAL
    // =================================================

    $display("\n====================================");
    $display(" FIM DA SIMULACAO ");
    $display("====================================");

    $finish;

end

endmodule

aula_(09)_may/lab8/wave.vcd
$date
	Sun May 10 22:09:19 2026
$end
$version
	Icarus Verilog
$end
$timescale
	1ps
$end
$scope module tb_decoder_ram_4x1 $end
$var wire 10 ! effective_addr [9:0] $end
$var wire 8 " dout3 [7:0] $end
$var wire 8 # dout2 [7:0] $end
$var wire 8 $ dout1 [7:0] $end
$var wire 8 % dout0 [7:0] $end
$var wire 1 & cs3 $end
$var wire 1 ' cs2 $end
$var wire 1 ( cs1 $end
$var wire 1 ) cs0 $end
$var reg 16 * addr [15:0] $end
$var reg 1 + clk $end
$var reg 8 , din [7:0] $end
$var reg 1 - we $end
$scope module dut $end
$var wire 16 . addr [15:0] $end
$var wire 1 ) cs0 $end
$var wire 1 ( cs1 $end
$var wire 1 ' cs2 $end
$var wire 1 & cs3 $end
$var wire 10 / effective_addr [9:0] $end
$upscope $end
$scope module ram0 $end
$var wire 10 0 addr [9:0] $end
$var wire 1 + clk $end
$var wire 1 ) cs $end
$var wire 8 1 din [7:0] $end
$var wire 8 2 dout [7:0] $end
$var wire 1 - we $end
$var reg 8 3 saida [7:0] $end
$var integer 32 4 i [31:0] $end
$upscope $end
$scope module ram1 $end
$var wire 10 5 addr [9:0] $end
$var wire 1 + clk $end
$var wire 1 ( cs $end
$var wire 8 6 din [7:0] $end
$var wire 8 7 dout [7:0] $end
$var wire 1 - we $end
$var reg 8 8 saida [7:0] $end
$var integer 32 9 i [31:0] $end
$upscope $end
$scope module ram2 $end
$var wire 10 : addr [9:0] $end
$var wire 1 + clk $end
$var wire 1 ' cs $end
$var wire 8 ; din [7:0] $end
$var wire 8 < dout [7:0] $end
$var wire 1 - we $end
$var reg 8 = saida [7:0] $end
$var integer 32 > i [31:0] $end
$upscope $end
$scope module ram3 $end
$var wire 10 ? addr [9:0] $end
$var wire 1 + clk $end
$var wire 1 & cs $end
$var wire 8 @ din [7:0] $end
$var wire 8 A dout [7:0] $end
$var wire 1 - we $end
$var reg 8 B saida [7:0] $end
$var integer 32 C i [31:0] $end
$upscope $end
$upscope $end
$enddefinitions $end
$comment Show the parameter values. $end
$dumpall
$end
#0
$dumpvars
b10000000000 C
b0 B
b0 A
b10100101 @
b10 ?
b10000000000 >
b0 =
b0 <
b10100101 ;
b10 :
b10000000000 9
b0 8
b0 7
b10100101 6
b10 5
b10000000000 4
b0 3
b0 2
b10100101 1
b10 0
b10 /
b10000000010 .
1-
b10100101 ,
0+
b10000000010 *
1)
0(
0'
0&
b0 %
b0 $
b0 #
b0 "
b10 !
$end
#5000
1+
#10000
b10000 !
b10000 /
b10000 0
b10000 5
b10000 :
b10000 ?
0)
1(
0+
b10110110 ,
b10110110 1
b10110110 6
b10110110 ;
b10110110 @
b100000010000 *
b100000010000 .
#15000
1+
#20000
b100000 !
b100000 /
b100000 0
b100000 5
b100000 :
b100000 ?
0(
1'
0+
b11000111 ,
b11000111 1
b11000111 6
b11000111 ;
b11000111 @
b110000100000 *
b110000100000 .
#25000
1+
#30000
b10101 !
b10101 /
b10101 0
b10101 5
b10101 :
b10101 ?
0'
1&
0+
b11011000 ,
b11011000 1
b11011000 6
b11011000 ;
b11011000 @
b1000000010101 *
b1000000010101 .
#35000
1+
#40000
b10 !
b10 /
b10 0
b10 5
b10 :
b10 ?
1)
0&
0+
b10000000010 *
b10000000010 .
0-
#45000
b10100101 %
b10100101 2
b10100101 3
1+
#50000
b10000 !
b10000 /
b10000 0
b10000 5
b10000 :
b10000 ?
0)
1(
0+
b100000010000 *
b100000010000 .
#55000
b10110110 $
b10110110 7
b10110110 8
1+
#60000
b100000 !
b100000 /
b100000 0
b100000 5
b100000 :
b100000 ?
0(
1'
0+
b110000100000 *
b110000100000 .
#65000
b11000111 #
b11000111 <
b11000111 =
1+
#70000
b10101 !
b10101 /
b10101 0
b10101 5
b10101 :
b10101 ?
0'
1&
0+
b1000000010101 *
b1000000010101 .
#75000
b11011000 "
b11011000 A
b11011000 B
1+
#80000
b10 !
b10 /
b10 0
b10 5
b10 :
b10 ?
1)
0&
0+
b1010101 ,
b1010101 1
b1010101 6
b1010101 ;
b1010101 @
b10000000010 *
b10000000010 .
1-
#85000
1+
#90000
0+
b10011001 ,
b10011001 1
b10011001 6
b10011001 ;
b10011001 @
#95000
b1010101 %
b1010101 2
b1010101 3
1+
#100000
0+
0-
#105000
b10011001 %
b10011001 2
b10011001 3
1+
#110000
b0 !
b0 /
b0 0
b0 5
b0 :
b0 ?
0)
1(
0+
b10001 ,
b10001 1
b10001 6
b10001 ;
b10001 @
b100000000000 *
b100000000000 .
1-
#115000
b0 $
b0 7
b0 8
1+
#120000
b1 !
b1 /
b1 0
b1 5
b1 :
b1 ?
0+
b100010 ,
b100010 1
b100010 6
b100010 ;
b100010 @
b100000000001 *
b100000000001 .
#125000
1+
#130000
b10 !
b10 /
b10 0
b10 5
b10 :
b10 ?
0+
b110011 ,
b110011 1
b110011 6
b110011 ;
b110011 @
b100000000010 *
b100000000010 .
#135000
1+
#140000
b11 !
b11 /
b11 0
b11 5
b11 :
b11 ?
0+
b1000100 ,
b1000100 1
b1000100 6
b1000100 ;
b1000100 @
b100000000011 *
b100000000011 .
#145000
1+
#150000
b0 !
b0 /
b0 0
b0 5
b0 :
b0 ?
0+
b100000000000 *
b100000000000 .
0-
#155000
b10001 $
b10001 7
b10001 8
1+
#160000
b1 !
b1 /
b1 0
b1 5
b1 :
b1 ?
0+
b100000000001 *
b100000000001 .
#165000
b100010 $
b100010 7
b100010 8
1+
#170000
b10 !
b10 /
b10 0
b10 5
b10 :
b10 ?
0+
b100000000010 *
b100000000010 .
#175000
b110011 $
b110011 7
b110011 8
1+
#180000
b11 !
b11 /
b11 0
b11 5
b11 :
b11 ?
0+
b100000000011 *
b100000000011 .
#185000
b1000100 $
b1000100 7
b1000100 8
1+
#190000
b0 !
b0 /
b0 0
b0 5
b0 :
b0 ?
0(
0+
b0 *
b0 .
#195000
1+
#200000
b1111111111 !
b1111111111 /
b1111111111 0
b1111111111 5
b1111111111 :
b1111111111 ?
0+
b1111111111111111 *
b1111111111111111 .
