aula_(15)_may/lab2/restoring_division_datapath.v
module restoring_division_datapath
#(
 parameter WIDTH = 8
)
(
 input wire clk,
 input wire rst,
 // controle
 input wire load,
 input wire [2:0] opcode,
 // operandos
 input wire [WIDTH-1:0] dividendo,
 input wire [WIDTH-1:0] divisor,
 // status para FSM
 output wire [WIDTH-1:0] a,
 output wire [WIDTH-1:0] n,
 // resultados
 output wire [WIDTH-1:0] quociente,
 output wire [WIDTH-1:0] resto

);
 // registradores internos
 reg [WIDTH-1:0] A; // resto
 reg [WIDTH-1:0] Q; // quociente/dividendo
 reg [WIDTH-1:0] M; // divisor
 reg [WIDTH-1:0] N; // contador

 // saídas

 assign a = A[WIDTH-1:0];
 assign n = N;
 assign quociente = Q;
 assign resto = A[WIDTH-1:0];


 // lógica principal

 always @(posedge clk or posedge rst) begin
    if(rst) begin
        A <= 0;
        Q <= 0;
        M <= 0;
        N <= 0;

    end else begin
    // LOAD
    if(load) begin
        A = 0;
        Q = dividendo;
        M = divisor;
        N = WIDTH;
    end else begin 
        case(opcode)
            3'b001:begin
                A = {A[WIDTH-1:0], Q[WIDTH-1]};
                Q = {Q[WIDTH-2:0], 1'b0};
            end
            3'b010: A = A + {1'b0, M};
            3'b011: A = A - {1'b0, M};
            3'b100: Q[0] = 1'b1;
            3'b101: Q[0] = 1'b0;
            3'b110: N = N - 1'b1;
        endcase
    end
    end
end
 // OPCODES


 
endmodule

aula_(15)_may/lab2/restoring_division_ctrl.v
module restoring_division_ctrl
#(parameter WIDTH = 8)
(
    input   wire                clk,
    input   wire                rst,
    input   wire                start,
    input   wire[WIDTH-1:0]     divisor,
    input   wire[WIDTH-1:0]     dividendo,
    input   wire[WIDTH-1:0]     a,
    input   wire[WIDTH-1:0]     n,
    output  reg                 load,  
    output  reg[2:0]           opcode,
    output  reg                 done,
    output  reg                 invalid_operation
);

localparam IDLE                  = 4'b0000;
localparam OPERAND_SANITIZE      = 4'b0001;
localparam LOAD_OPERANDS         = 4'b0010;
localparam SHIFT_AQ              = 4'b0011;
localparam A_MODIFY              = 4'b0100;
localparam Q_BIT_FLIP            = 4'b0101;
localparam N_SUBTRATION          = 4'b0110;
localparam N_VERIFICATION        = 4'b0111;
localparam A_CORRECTION          = 4'b1000;
localparam FINISH                = 4'b1001;

reg [3:0] state, next_state;

always @(posedge clk or posedge rst) begin
    if (rst)
        state <= IDLE;
    else
        state <= next_state;
end


always @(*) begin //decode signals
    load = 0;
    opcode = 3'b00;
    done = 0;
    invalid_operation = 0;
    case (state)
        OPERAND_SANITIZE: begin
            invalid_operation = (divisor == {WIDTH{1'b0}});
        end
        LOAD_OPERANDS: 
            load = 1;
        SHIFT_AQ:
            opcode = 3'b001; //shift
        A_MODIFY:
            if(a[WIDTH-1]) begin
                opcode = 3'b010; //soma
            end else begin
                opcode = 3'b011; //sub
            end
        Q_BIT_FLIP: 
             if(a[WIDTH-1]) begin
                opcode = 3'b100; //set 1 em Q[1]
            end else begin
                opcode = 3'b101; //set 0 em Q[0]
            end
        N_SUBTRATION: opcode = 3'b110; //subtrai n
        A_CORRECTION: 
            if(a[WIDTH-1]) begin
                opcode = 3'b010; //soma
            end
        FINISH: done = 1;
    endcase
        
end

always @(*) begin //transaction logic
    next_state = state;
    case (state) 
        IDLE:
            if(start) begin
                next_state = OPERAND_SANITIZE;
            end
        OPERAND_SANITIZE: 
            if(!invalid_operation) begin
                next_state = LOAD_OPERANDS;
            end
        LOAD_OPERANDS:  next_state = SHIFT_AQ;
        SHIFT_AQ:       next_state = A_MODIFY;
        A_MODIFY:       next_state = Q_BIT_FLIP;
        Q_BIT_FLIP:     next_state = N_SUBTRATION;
        N_SUBTRATION:   next_state = N_VERIFICATION;
        N_VERIFICATION: next_state = (n==0) ? A_CORRECTION : SHIFT_AQ;
        A_CORRECTION :  next_state = FINISH;
        FINISH:         next_state = IDLE;
    endcase
end

endmodule

aula_(15)_may/lab2/restoring_division.v

module restoring_division_top
#(
 parameter WIDTH = 8
)
(
 input wire clk,
 input wire rst,
 input wire start,
 input wire [WIDTH-1:0] dividendo,
 input wire [WIDTH-1:0] divisor,
 output wire [WIDTH-1:0] quociente,
 output wire [WIDTH-1:0] resto,
 output wire done,
 // flags
 output wire div_zero
);

 // sinais internos
 wire load;
 wire [2:0] opcode;
 wire [WIDTH-1:0] a;
 wire [WIDTH-1:0] n;

 // CONTROL UNIT

 restoring_division_ctrl #(.WIDTH(WIDTH)) CTRL
 (
 .clk(clk),
 .rst(rst),
 .start(start),
 .divisor(divisor),
 .dividendo(dividendo),
 .a(a),
 .n(n),
 .load(load),
 .opcode(opcode),
 .done(done),
 .invalid_operation(div_zero)
 );

 // DATAPATH

 restoring_division_datapath #( .WIDTH(WIDTH) ) DP (
 .clk(clk),
 .rst(rst),
 .load(load),
 .opcode(opcode),
 .dividendo(dividendo),
 .divisor(divisor),
 .a(a),
 .n(n),
 .quociente(quociente),
 .resto(resto)
 );

endmodule

aula_(15)_may/lab2/restoring_division_tb.v
`timescale 1ns/1ps

module restoring_division_tb;

 parameter WIDTH = 4;

 // sinais
 reg clk;
 reg rst;
 reg start;
 reg [WIDTH-1:0] dividendo;
 reg [WIDTH-1:0] divisor;
 wire [WIDTH-1:0] quociente;
 wire [WIDTH-1:0] resto;
 wire done;
 wire div_zero;
 wire quociente_zero;
 wire resto_zero;
 wire resto_negativo;

 reg [WIDTH-1:0] quociente_expected;
 reg [WIDTH-1:0] resto_expected;
 // DUT

 restoring_division_top #(.WIDTH(WIDTH)) DUT
 ( .clk(clk),
 .rst(rst),
 .start(start),
 .dividendo(dividendo),
 .divisor(divisor),
 .quociente(quociente),
 .resto(resto),
 .done(done)
 );

always #5 clk = ~clk;

task expected_divide;

 input [WIDTH-1:0] opA;
 input [WIDTH-1:0] opB;
begin

 @(posedge clk);

 start = 1'b1;
 dividendo = opA;
 divisor = opB;

 while (!done) begin
    @(posedge clk);
 end
 
 quociente_expected = dividendo / divisor;
 resto_expected = dividendo % divisor;
 
 $display("Quociente ex: %d, Quociente got: %d", quociente_expected, quociente );
 $display("resto ex: %d, resto got: %d", resto_expected, resto );

end

endtask




 // sequência de testes

 initial
 begin
 clk = 0;
 $dumpfile("wave.vcd");
 $dumpvars(0, restoring_division_tb);

 // inicialização

 rst = 1'b1;

 start = 0;

 dividendo = 0;
 divisor = 0;

 #20;

 rst = 1'b0;

 #20;

 // CASOS OBRIGATÓRIOS
 expected_divide(8'd11, 8'd3);

 // fim

 $display("FIM DA SIMULACAO");
 #20;

 $finish;

 end

endmodule

// iverilog -o sim restoring_division_tb tb_restoring_division.v restoring_division_top.v restoring_division_ctrl.v restoring_division_datapath.v

aula_(15)_may/lab2/wave.vcd
$date
	Sat May 16 14:40:20 2026
$end
$version
	Icarus Verilog
$end
$timescale
	1ps
$end
$scope module restoring_division_tb $end
$var wire 4 ! resto [3:0] $end
$var wire 4 " quociente [3:0] $end
$var wire 1 # done $end
$var parameter 32 $ WIDTH $end
$var reg 1 % clk $end
$var reg 4 & dividendo [3:0] $end
$var reg 4 ' divisor [3:0] $end
$var reg 4 ( quociente_expected [3:0] $end
$var reg 4 ) resto_expected [3:0] $end
$var reg 1 * rst $end
$var reg 1 + start $end
$scope module DUT $end
$var wire 1 % clk $end
$var wire 4 , dividendo [3:0] $end
$var wire 4 - divisor [3:0] $end
$var wire 1 * rst $end
$var wire 1 + start $end
$var wire 4 . resto [3:0] $end
$var wire 4 / quociente [3:0] $end
$var wire 3 0 opcode [2:0] $end
$var wire 4 1 n [3:0] $end
$var wire 1 2 load $end
$var wire 1 # done $end
$var wire 1 3 div_zero $end
$var wire 4 4 a [3:0] $end
$var parameter 32 5 WIDTH $end
$scope module CTRL $end
$var wire 1 % clk $end
$var wire 4 6 dividendo [3:0] $end
$var wire 4 7 divisor [3:0] $end
$var wire 1 * rst $end
$var wire 1 + start $end
$var wire 4 8 n [3:0] $end
$var wire 4 9 a [3:0] $end
$var parameter 4 : A_CORRECTION $end
$var parameter 4 ; A_MODIFY $end
$var parameter 4 < FINISH $end
$var parameter 4 = IDLE $end
$var parameter 4 > LOAD_OPERANDS $end
$var parameter 4 ? N_SUBTRATION $end
$var parameter 4 @ N_VERIFICATION $end
$var parameter 4 A OPERAND_SANITIZE $end
$var parameter 4 B Q_BIT_FLIP $end
$var parameter 4 C SHIFT_AQ $end
$var parameter 32 D WIDTH $end
$var reg 1 # done $end
$var reg 1 3 invalid_operation $end
$var reg 1 2 load $end
$var reg 4 E next_state [3:0] $end
$var reg 3 F opcode [2:0] $end
$var reg 4 G state [3:0] $end
$upscope $end
$scope module DP $end
$var wire 4 H a [3:0] $end
$var wire 1 % clk $end
$var wire 4 I dividendo [3:0] $end
$var wire 4 J divisor [3:0] $end
$var wire 1 2 load $end
$var wire 4 K n [3:0] $end
$var wire 3 L opcode [2:0] $end
$var wire 4 M quociente [3:0] $end
$var wire 4 N resto [3:0] $end
$var wire 1 * rst $end
$var parameter 32 O WIDTH $end
$var reg 4 P A [3:0] $end
$var reg 4 Q M [3:0] $end
$var reg 4 R N [3:0] $end
$var reg 4 S Q [3:0] $end
$upscope $end
$upscope $end
$scope task expected_divide $end
$var reg 4 T opA [3:0] $end
$var reg 4 U opB [3:0] $end
$upscope $end
$upscope $end
$enddefinitions $end
$comment Show the parameter values. $end
$dumpall
b100 O
b100 D
b11 C
b101 B
b1 A
b111 @
b110 ?
b10 >
b0 =
b1001 <
b100 ;
b1000 :
b100 5
b100 $
$end
#0
$dumpvars
bx U
bx T
b0 S
b0 R
b0 Q
b0 P
b0 N
b0 M
b0 L
b0 K
b0 J
b0 I
b0 H
b0 G
b0 F
b0 E
b0 9
b0 8
b0 7
b0 6
b0 4
03
02
b0 1
b0 0
b0 /
b0 .
b0 -
b0 ,
0+
1*
bx )
bx (
b0 '
b0 &
0%
0#
b0 "
b0 !
$end
#5000
1%
#10000
0%
#15000
1%
#20000
0%
0*
#25000
1%
#30000
0%
#35000
1%
#40000
0%
b11 U
b1011 T
#45000
b1 E
b11 '
b11 -
b11 7
b11 J
b1011 &
b1011 ,
b1011 6
b1011 I
1+
1%
#50000
0%
#55000
b10 E
b1 G
1%
#60000
0%
#65000
b11 E
12
b10 G
1%
#70000
0%
#75000
b1 0
b1 F
b1 L
02
b11 G
b100 E
b100 1
b100 8
b100 K
b100 R
b11 Q
b1011 "
b1011 /
b1011 M
b1011 S
1%
#80000
0%
#85000
b101 E
b100 G
b11 0
b11 F
b11 L
b110 "
b110 /
b110 M
b110 S
b1 !
b1 .
b1 N
b1 4
b1 9
b1 H
b1 P
1%
#90000
0%
#95000
b110 E
b101 G
b100 0
b100 F
b100 L
b1110 !
b1110 .
b1110 N
b1110 4
b1110 9
b1110 H
b1110 P
1%
#100000
0%
#105000
b111 E
b110 0
b110 F
b110 L
b110 G
b111 "
b111 /
b111 M
b111 S
1%
#110000
0%
#115000
b0 0
b0 F
b0 L
b111 G
b11 E
b11 1
b11 8
b11 K
b11 R
1%
#120000
0%
#125000
b100 E
b1 0
b1 F
b1 L
b11 G
1%
#130000
0%
#135000
b101 E
b100 G
b10 0
b10 F
b10 L
b1110 "
b1110 /
b1110 M
b1110 S
b1100 !
b1100 .
b1100 N
b1100 4
b1100 9
b1100 H
b1100 P
1%
#140000
0%
#145000
b110 E
b101 G
b100 0
b100 F
b100 L
b1111 !
b1111 .
b1111 N
b1111 4
b1111 9
b1111 H
b1111 P
1%
#150000
0%
#155000
b111 E
b110 0
b110 F
b110 L
b110 G
b1111 "
b1111 /
b1111 M
b1111 S
1%
#160000
0%
#165000
b0 0
b0 F
b0 L
b111 G
b11 E
b10 1
b10 8
b10 K
b10 R
1%
#170000
0%
#175000
b100 E
b1 0
b1 F
b1 L
b11 G
1%
#180000
0%
#185000
b101 E
b10 0
b10 F
b10 L
b100 G
b1110 "
b1110 /
b1110 M
b1110 S
1%
#190000
0%
#195000
b110 E
b101 G
b101 0
b101 F
b101 L
b10 !
b10 .
b10 N
b10 4
b10 9
b10 H
b10 P
1%
#200000
0%
#205000
b111 E
b110 0
b110 F
b110 L
b110 G
1%
#210000
0%
#215000
b0 0
b0 F
b0 L
b111 G
b11 E
b1 1
b1 8
b1 K
b1 R
1%
#220000
0%
#225000
b100 E
b1 0
b1 F
b1 L
b11 G
1%
#230000
0%
#235000
b101 E
b100 G
b11 0
b11 F
b11 L
b1100 "
b1100 /
b1100 M
b1100 S
b101 !
b101 .
b101 N
b101 4
b101 9
b101 H
b101 P
1%
#240000
0%
#245000
b110 E
b101 G
b101 0
b101 F
b101 L
b10 !
b10 .
b10 N
b10 4
b10 9
b10 H
b10 P
1%
#250000
0%
#255000
b111 E
b110 0
b110 F
b110 L
b110 G
1%
#260000
0%
#265000
b0 0
b0 F
b0 L
b111 G
b1000 E
b0 1
b0 8
b0 K
b0 R
1%
#270000
0%
#275000
b1001 E
b1000 G
1%
#280000
0%
#285000
b0 E
1#
b1001 G
1%
#290000
0%
#295000
b1 E
0#
b0 G
b10 )
b11 (
1%
#300000
0%
#305000
b10 E
b1 G
1%
#310000
0%
#315000
b11 E
12
b10 G
1%
