aula_(09)_may/lab7/single_port_ram.v
module single_port_ram(
    input wire     clk,
    input wire     we,
    input wire     cs,
    input wire [9:0] addr,
    input wire [7:0] din,
    output wire [7:0] dout
 );

 reg [7:0] mem [0:1023];
 reg [7:0] saida;

 assign dout = saida;

 integer i;

 initial begin
    saida = 8'd0;

    for(i = 0; i < 1024; i = i + 1) begin
        mem[i] = 8'd0;
    end

 end


 always @(posedge clk) begin
    if (cs) begin
        if (we) begin 
            mem[addr] <= din;
        end
        saida <= mem[addr];
    end
 end

endmodule

aula_(09)_may/lab7/decoder_ram.v
module decoder_ram (
    input wire [15:0] addr,
    output wire [9:0] effective_addr,
    output wire cs
 );

 assign cs = (addr >= 16'h0000 && addr <= 16'h03FF);
 assign effective_addr = addr[9:0];

endmodule

aula_(09)_may/lab7/tb_decoder_ram.v
`timescale 1ns/1ps

module tb_decoder_ram;

reg clk;
reg we;
wire cs;

reg [15:0] addr;
reg [7:0] data_in;

wire [9:0] effective_addr;
wire [7:0] data_out;



decoder_ram uut (
    .addr(addr),
    .effective_addr(effective_addr),
    .cs(cs)
);

single_port_ram ram0 (
    .clk(clk),
    .we(we),
    .cs(cs),
    .addr(effective_addr),
    .din(data_in),
    .dout(data_out)
 );

always #5 clk = ~clk;

initial begin

    $dumpfile("wave.vcd");
    $dumpvars(0, tb_decoder_ram);


    clk = 0;
    we = 0;
    addr = 0;
    data_in = 0;

    $monitor("Tempo=%0t | WE=%b | ADDR=%h | data_in=%h | data_out=%h",
              $time,
              we,
              addr,
              data_in,
              data_out);

    we = 1;
    addr = 16'h0000;
    data_in  = 8'hFF;
    #10;

    addr = 16'h0001;
    data_in  = 8'hAA;
    #10;

    addr = 16'h03FF;
    data_in  = 8'h33;
    #10;

    we = 0;
    data_in  = 8'h44;
    addr = 16'h0000;
    #10;

    data_in  = 8'h55;
    addr = 16'h0001;
    #10;

    data_in  = 8'h66;
    addr = 16'h03FF;
    #10;

    we = 1;

    addr = 16'h0400;
    data_in  = 8'h55;
    #10;

    we = 0;
    data_in  = 8'h77;
    addr = 16'h0350;
    #10;

    $display(" FIM DA SIMULACAO ");

    $finish;

end

endmodule

aula_(09)_may/lab7/wave.vcd
$date
	Sun May 10 21:51:33 2026
$end
$version
	Icarus Verilog
$end
$timescale
	1ps
$end
$scope module tb_decoder_ram $end
$var wire 10 ! effective_addr [9:0] $end
$var wire 8 " data_out [7:0] $end
$var wire 1 # cs $end
$var reg 16 $ addr [15:0] $end
$var reg 1 % clk $end
$var reg 8 & data_in [7:0] $end
$var reg 1 ' we $end
$scope module ram0 $end
$var wire 1 % clk $end
$var wire 8 ( din [7:0] $end
$var wire 8 ) dout [7:0] $end
$var wire 1 ' we $end
$var wire 1 # cs $end
$var wire 10 * addr [9:0] $end
$var reg 8 + saida [7:0] $end
$var integer 32 , i [31:0] $end
$upscope $end
$scope module uut $end
$var wire 16 - addr [15:0] $end
$var wire 1 # cs $end
$var wire 10 . effective_addr [9:0] $end
$upscope $end
$upscope $end
$enddefinitions $end
$comment Show the parameter values. $end
$dumpall
$end
#0
$dumpvars
b0 .
b0 -
b10000000000 ,
b0 +
b0 *
b0 )
b11111111 (
1'
b11111111 &
0%
b0 $
1#
b0 "
b0 !
$end
#5000
1%
#10000
b1 !
b1 *
b1 .
0%
b10101010 &
b10101010 (
b1 $
b1 -
#15000
1%
#20000
b1111111111 !
b1111111111 *
b1111111111 .
0%
b110011 &
b110011 (
b1111111111 $
b1111111111 -
#25000
1%
#30000
b0 !
b0 *
b0 .
0%
b0 $
b0 -
b1000100 &
b1000100 (
0'
#35000
b11111111 "
b11111111 )
b11111111 +
1%
#40000
b1 !
b1 *
b1 .
0%
b1 $
b1 -
b1010101 &
b1010101 (
#45000
b10101010 "
b10101010 )
b10101010 +
1%
#50000
b1111111111 !
b1111111111 *
b1111111111 .
0%
b1111111111 $
b1111111111 -
b1100110 &
b1100110 (
#55000
b110011 "
b110011 )
b110011 +
1%
#60000
0#
b0 !
b0 *
b0 .
0%
b1010101 &
b1010101 (
b10000000000 $
b10000000000 -
1'
#65000
1%
#70000
1#
b1101010000 !
b1101010000 *
b1101010000 .
0%
b1101010000 $
b1101010000 -
b1110111 &
b1110111 (
0'
#75000
b0 "
b0 )
b0 +
1%
