aula_(09)_may/lab2/alu.v
module alu
#(parameter WIDTH = 8)
(
    input wire[WIDTH-1:0] in_a,
    input wire[WIDTH-1:0] in_b,
    input wire[2:0]       opcode,
    output reg[WIDTH-1:0]  alu_out,
    output wire            a_is_zero
);

assign a_is_zero = (in_a == {WIDTH{1'b0}});

always @(*)
begin
    case (opcode)
        3'b000: alu_out = (in_a + in_b);
        3'b001: alu_out = in_a;
        3'b010: alu_out = in_a;
        3'b011: alu_out = (in_a & in_b);
        3'b100: alu_out = (in_a ^ in_b);
        3'b101: alu_out = in_b;
        3'b110: alu_out = in_a;
        3'b111: alu_out = in_a;
    endcase
end


endmodule

aula_(09)_may/lab3/ram_dual.v
module ram_dual (
    input  wire        clk,
    input  wire        we_a,
    input  wire        cs,
    input  wire [4:0]  addr_wr_a,
    input  wire [7:0]  data_wr_a,
    input  wire [4:0]  addr_rd_b,
    output reg  [7:0]  data_rd_a,
    output reg  [7:0]  data_rd_b
);

    reg [7:0] ram [0:31];

    always @(posedge clk) begin
        if(cs) begin 
            if (we_a) begin
                ram[addr_wr_a] <= addr_wr_a;
            end else begin 
                data_rd_a <= ram[addr_wr_a];
            end

            data_rd_b <= ram[addr_rd_b];
        end
    end

    initial begin
        $readmemh("mem_dados.txt",ram);
    end

endmodule

aula_(09)_may/lab2/ram_single.v
module ram_single (
    input  wire         clk,
    input  wire         cs,
    input  wire         we,
    input  wire [4:0]   addr,
    input  wire [7:0]  data_in,
    output reg  [7:0]  data_out
);

    reg [7:0] ram [0:31];

    always @(posedge clk) begin
        if(cs) begin 
            if (we) begin
                ram[addr] <= data_in;
                data_out  <= data_in;
            end

            else begin
                data_out <= ram[addr];
            end
        end
    end

    initial begin
        $readmemh("mem_s_dados.txt",ram);
    end

endmodule

aula_(09)_may/lab2/top.v
module top(
    input wire [4:0] endereco_saida,
    input wire we_resultado,
    input wire [4:0] enderecoA,
    input wire [4:0] enderecoB,
    input wire clk,
    input wire cs,
    input wire [7:0] dado_in,
    input wire we_mem_in,
    input wire [2:0] opcode,
    output wire [7:0] saida,
    output wire [7:0] sdadoA,
    output wire [7:0] sdadoB,
    output wire [7:0] s_ula
);

    localparam WIDTH=8;

    ram_single RAM_SP (
        .clk(clk),
        .cs(cs),
        .we(we_resultado),
        .addr(endereco_saida),
        .data_in(s_ula),
        .data_out(saida)
    );

    ram_dual RAM_DP (
        .clk(clk),
        .cs(cs),
        .addr_wr_a(enderecoA),
        .addr_rd_b(enderecoB),
        .data_wr_a(dado_in),
        .we_a(we_mem_in),
        .data_rd_a(sdadoA),
        .data_rd_b(sdadoB)
    );

    alu #( .WIDTH ( WIDTH ))
    alu_inst
    (
        .opcode    (opcode ),
        .in_a      (sdadoA ),
        .in_b      (sdadoB ),
        .alu_out   (s_ula) 
    );

endmodule

aula_(09)_may/lab2/top_tb.v
module top_tb();

    reg [4:0] endereco_saida;
    reg we_resultado;
    reg [4:0] enderecoA;
    reg [4:0] enderecoB;
    reg clk;
    reg [7:0] dado_in;
    reg we_mem_in;
    wire [7:0] saida;
    wire [7:0] sdadoA;
    wire [7:0] sdadoB;
    wire [7:0] s_ula;
    reg cs;
    reg [2:0] opcode;
    initial begin
        clk = 0;
        forever #10 clk = ~clk;
    end



    top dut(
        .endereco_saida(endereco_saida),
        .we_resultado(we_resultado),
        .enderecoA(enderecoA),
        .enderecoB(enderecoB),
        .clk(clk),
        .cs(cs),
        .dado_in(dado_in),
        .we_mem_in(we_mem_in),
        .opcode(opcode),
        .saida(saida),
        .sdadoA(sdadoA),
        .sdadoB(sdadoB),
        .s_ula(s_ula)
    );

    initial begin
        $monitor(
            "T=%0t | A=%d B=%d | dadoA=%d dadoB=%d | opcode=%d | ula=%d | saida=%d",
            $time,
            enderecoA,
            enderecoB,
            sdadoA,
            sdadoB,
            opcode,
            s_ula,
            saida
        );
    end

    initial begin
        $dumpfile("wave.vcd");
        $dumpvars(0, top_tb);
    end

    initial begin

        //-------------------------------------
        // Inicialização
        //-------------------------------------
        endereco_saida = 0;
        cs = 1;
        opcode = 0;
        enderecoA      = 8'h08;
        enderecoB      = 8'h09;
        dado_in        = 8'h04;
        we_mem_in      = 0;
        we_resultado   = 0;
        #45;

        endereco_saida = 1;
        enderecoA      = 8'h00;
        we_mem_in      = 1;
        #20;

        enderecoB      = 8'h06;
        endereco_saida = 2;
        we_mem_in      = 0;
        dado_in        = 8'h05;
        #20;
        enderecoA      = 8'h01;
        #5
        we_mem_in      = 1;

        #15;
        we_mem_in      = 0;
        endereco_saida = 5;
        endereco_saida = 0;
        //-------------------------------------
        // Escreve 10 na RAM dual endereço 0
        //-------------------------------------
        @(posedge clk);
        enderecoA   = 5'd0;
        dado_in     = 8'd10;
        we_mem_in   = 1'b1;

        @(posedge clk);
        we_mem_in   = 1'b0;

        //-------------------------------------
        // Escreve 20 na RAM dual endereço 1
        //-------------------------------------
        @(posedge clk);
        enderecoA   = 5'd1;
        dado_in     = 8'd20;
        we_mem_in   = 1'b1;

        @(posedge clk);
        we_mem_in   = 1'b0;

        //-------------------------------------
        // Lê posições 0 e 1
        //-------------------------------------
        @(posedge clk);
        enderecoA = 5'd0;
        enderecoB = 5'd1;

        //-------------------------------------
        // Teste ALU
        //-------------------------------------
        // opcode = 0 -> soma
        //-------------------------------------
        opcode = 3'd0;

        #20;

        //-------------------------------------
        // Salva resultado da ALU
        //-------------------------------------
        @(posedge clk);
        endereco_saida = 5'd2;
        we_resultado   = 1'b1;

        @(posedge clk);
        we_resultado   = 1'b0;

        //-------------------------------------
        // Espera
        //-------------------------------------
        #50;

        $display("Fim da simulacao");
        $finish;

    end

endmodule

aula_(09)_may/lab2/wave.vcd
$date
	Sat May  9 18:40:22 2026
$end
$version
	Icarus Verilog
$end
$timescale
	1s
$end
$scope module top_tb $end
$var wire 8 ! sdadoB [7:0] $end
$var wire 8 " sdadoA [7:0] $end
$var wire 8 # saida [7:0] $end
$var wire 8 $ s_ula [7:0] $end
$var reg 1 % clk $end
$var reg 1 & cs $end
$var reg 8 ' dado_in [7:0] $end
$var reg 5 ( enderecoA [4:0] $end
$var reg 5 ) enderecoB [4:0] $end
$var reg 5 * endereco_saida [4:0] $end
$var reg 3 + opcode [2:0] $end
$var reg 1 , we_mem_in $end
$var reg 1 - we_resultado $end
$scope module dut $end
$var wire 1 % clk $end
$var wire 1 & cs $end
$var wire 8 . dado_in [7:0] $end
$var wire 5 / enderecoA [4:0] $end
$var wire 5 0 enderecoB [4:0] $end
$var wire 5 1 endereco_saida [4:0] $end
$var wire 3 2 opcode [2:0] $end
$var wire 1 , we_mem_in $end
$var wire 1 - we_resultado $end
$var wire 8 3 sdadoB [7:0] $end
$var wire 8 4 sdadoA [7:0] $end
$var wire 8 5 saida [7:0] $end
$var wire 8 6 s_ula [7:0] $end
$var parameter 32 7 WIDTH $end
$scope module RAM_DP $end
$var wire 5 8 addr_rd_b [4:0] $end
$var wire 5 9 addr_wr_a [4:0] $end
$var wire 1 % clk $end
$var wire 1 & cs $end
$var wire 8 : data_wr_a [7:0] $end
$var wire 1 , we_a $end
$var reg 8 ; data_rd_a [7:0] $end
$var reg 8 < data_rd_b [7:0] $end
$upscope $end
$scope module RAM_SP $end
$var wire 5 = addr [4:0] $end
$var wire 1 % clk $end
$var wire 1 & cs $end
$var wire 1 - we $end
$var wire 8 > data_in [7:0] $end
$var reg 8 ? data_out [7:0] $end
$upscope $end
$scope module alu_inst $end
$var wire 8 @ in_a [7:0] $end
$var wire 8 A in_b [7:0] $end
$var wire 3 B opcode [2:0] $end
$var wire 1 C a_is_zero $end
$var parameter 32 D WIDTH $end
$var reg 8 E alu_out [7:0] $end
$upscope $end
$upscope $end
$upscope $end
$enddefinitions $end
$comment Show the parameter values. $end
$dumpall
b1000 D
b1000 7
$end
#0
$dumpvars
bx E
xC
b0 B
bx A
bx @
bx ?
bx >
b0 =
bx <
bx ;
b100 :
b1000 9
b1001 8
bx 6
bx 5
bx 4
bx 3
b0 2
b0 1
b1001 0
b1000 /
b100 .
0-
0,
b0 +
b0 *
b1001 )
b1000 (
b100 '
1&
0%
bx $
bx #
bx "
bx !
$end
#10
b1011001 $
b1011001 6
b1011001 >
b1011001 E
b100011 #
b100011 5
b100011 ?
b110000 !
b110000 3
b110000 <
b110000 A
0C
b101001 "
b101001 4
b101001 ;
b101001 @
1%
#20
0%
#30
1%
#40
0%
#45
1,
b0 (
b0 /
b0 9
b1 *
b1 1
b1 =
#50
1%
#60
0%
#65
b101 '
b101 .
b101 :
0,
b10 *
b10 1
b10 =
b110 )
b110 0
b110 8
#70
b100111 $
b100111 6
b100111 >
b100111 E
b100111 !
b100111 3
b100111 <
b100111 A
1C
b0 "
b0 4
b0 ;
b0 @
1%
#80
0%
#85
b1 (
b1 /
b1 9
#90
1,
1%
#100
0%
#105
b0 *
b0 1
b0 =
0,
#110
1,
b1010 '
b1010 .
b1010 :
b0 (
b0 /
b0 9
1%
#120
0%
#130
0,
1%
#140
0%
#150
1,
b10100 '
b10100 .
b10100 :
b1 (
b1 /
b1 9
1%
#160
0%
#170
0,
1%
#180
0%
#190
b1 $
b1 6
b1 >
b1 E
b1 !
b1 3
b1 <
b1 A
b1 )
b1 0
b1 8
b0 (
b0 /
b0 9
1%
#200
0%
#210
b1 #
b1 5
b1 ?
1-
b10 *
b10 1
b10 =
1%
#220
0%
#230
0-
1%
