aula_(11_12)_april/lab3/compare.v
module compare
#(
    parameter COUNTER_WIDTH = 16
)
(
    input [COUNTER_WIDTH-1:0] default_value, 
    input [COUNTER_WIDTH-1:0] counter_i,
    output isEqual
);

reg [COUNTER_WIDTH-1:0] counter;

assign isEqual = (default_value == counter_i);


endmodule

aula_(11_12)_april/lab3/counter.v
module counter
#(
    parameter COUNTER_WIDTH = 16
)
(
    input  clk, 
    input  rst,
    input  en_n,
    output reg [COUNTER_WIDTH-1:0] counter_o 
);


always @(posedge clk) begin
    if (rst == 1'b1) begin
        counter_o <= {COUNTER_WIDTH{1'b0}};
    end else begin
        if (en_n == 1'b1)
            counter_o <= counter_o + 1;
    end
end

endmodule

aula_(11_12)_april/lab3/circuit12.v

module circuit12 
#(
    parameter COUNTER_MAX = 16,
    parameter COUNTER_WIDTH = $clog2(COUNTER_MAX)
)(
    input  clk_i,
    input  rst_i,
    input [COUNTER_WIDTH-1:0] default_value,
    output reg out
);

wire [COUNTER_WIDTH-1:0] counter;
wire en;

counter #(.COUNTER_WIDTH(COUNTER_WIDTH)) counter_inst(
    .clk(clk_i),
    .rst(rst_i),
    .en_n(!en),
    .counter_o(counter)
);


compare #(.COUNTER_WIDTH(COUNTER_WIDTH)) compare_inst
(
    .default_value(default_value), 
    .counter_i(counter),
    .isEqual(en)
);

always @(posedge clk_i) begin
    out <= en;
end

endmodule

aula_(11_12)_april/lab3/circuit12_tb.v
`timescale 1ns/1ps

module circuit12_tb;

parameter COUNTER_MAX = 16;
localparam COUNTER_WIDTH = $clog2(COUNTER_MAX);

// sinais
reg clk;
reg rst;
reg [COUNTER_WIDTH-1:0] default_value;
wire out;

// instância do DUT
circuit12 #(
    .COUNTER_MAX(COUNTER_MAX)
) dut (
    .clk_i(clk),
    .rst_i(rst),
    .default_value(default_value),
    .out(out)
);

// clock: 10ns período
always #5 clk = ~clk;

// estímulos
initial begin
    // inicialização
    clk = 0;
    rst = 1;
    default_value = 5;

    // reset ativo
    #20;
    rst = 0;

    // roda um tempo
    #200;

    // muda valor de comparação
    default_value = 10;

    #200;

    // novo teste
    default_value = 3;

    #200;

    $finish;
end

// monitoramento
initial begin
    $dumpfile("circuit12.vcd");
    $dumpvars(0, circuit12_tb);
    
    $display("clk\trst\tcounter\tdefault\tout");
    $monitor("%b\t%b\t%d\t%d\t%b",
             clk, rst, dut.counter, default_value, out);
    
end


endmodule

aula_(11_12)_april/lab3/circuit12.vcd
$date
	Sat Apr 11 15:29:24 2026
$end
$version
	Icarus Verilog
$end
$timescale
	1ps
$end
$scope module circuit12_tb $end
$var wire 1 ! out $end
$var parameter 32 " COUNTER_MAX $end
$var parameter 32 # COUNTER_WIDTH $end
$var reg 1 $ clk $end
$var reg 4 % default_value [3:0] $end
$var reg 1 & rst $end
$scope module dut $end
$var wire 1 $ clk_i $end
$var wire 4 ' default_value [3:0] $end
$var wire 1 & rst_i $end
$var wire 1 ( en $end
$var wire 4 ) counter [3:0] $end
$var parameter 32 * COUNTER_MAX $end
$var parameter 32 + COUNTER_WIDTH $end
$var reg 1 ! out $end
$scope module compare_inst $end
$var wire 4 , default_value [3:0] $end
$var wire 1 ( isEqual $end
$var wire 4 - counter_i [3:0] $end
$var parameter 32 . COUNTER_WIDTH $end
$upscope $end
$scope module counter_inst $end
$var wire 1 $ clk $end
$var wire 1 / en_n $end
$var wire 1 & rst $end
$var parameter 32 0 COUNTER_WIDTH $end
$var reg 4 1 counter_o [3:0] $end
$upscope $end
$upscope $end
$upscope $end
$enddefinitions $end
$comment Show the parameter values. $end
$dumpall
b100 0
b100 .
b100 +
b10000 *
b100 #
b10000 "
$end
#0
$dumpvars
bx 1
x/
bx -
b101 ,
bx )
x(
b101 '
1&
b101 %
0$
x!
$end
#5000
1/
0(
b0 )
b0 -
b0 1
1$
#10000
0$
#15000
0!
1$
#20000
0$
0&
#25000
b1 )
b1 -
b1 1
1$
#30000
0$
#35000
b10 )
b10 -
b10 1
1$
#40000
0$
#45000
b11 )
b11 -
b11 1
1$
#50000
0$
#55000
b100 )
b100 -
b100 1
1$
#60000
0$
#65000
0/
1(
b101 )
b101 -
b101 1
1$
#70000
0$
#75000
1!
1$
#80000
0$
#85000
1$
#90000
0$
#95000
1$
#100000
0$
#105000
1$
#110000
0$
#115000
1$
#120000
0$
#125000
1$
#130000
0$
#135000
1$
#140000
0$
#145000
1$
#150000
0$
#155000
1$
#160000
0$
#165000
1$
#170000
0$
#175000
1$
#180000
0$
#185000
1$
#190000
0$
#195000
1$
#200000
0$
#205000
1$
#210000
0$
#215000
1$
#220000
0$
1/
0(
b1010 %
b1010 '
b1010 ,
#225000
b110 )
b110 -
b110 1
0!
1$
#230000
0$
#235000
b111 )
b111 -
b111 1
1$
#240000
0$
#245000
b1000 )
b1000 -
b1000 1
1$
#250000
0$
#255000
b1001 )
b1001 -
b1001 1
1$
#260000
0$
#265000
0/
1(
b1010 )
b1010 -
b1010 1
1$
#270000
0$
#275000
1!
1$
#280000
0$
#285000
1$
#290000
0$
#295000
1$
#300000
0$
#305000
1$
#310000
0$
#315000
1$
#320000
0$
#325000
1$
#330000
0$
#335000
1$
#340000
0$
#345000
1$
#350000
0$
#355000
1$
#360000
0$
#365000
1$
#370000
0$
#375000
1$
#380000
0$
#385000
1$
#390000
0$
#395000
1$
#400000
0$
#405000
1$
#410000
0$
#415000
1$
#420000
0$
1/
0(
b11 %
b11 '
b11 ,
#425000
b1011 )
b1011 -
b1011 1
0!
1$
#430000
0$
#435000
b1100 )
b1100 -
b1100 1
1$
#440000
0$
#445000
b1101 )
b1101 -
b1101 1
1$
#450000
0$
#455000
b1110 )
b1110 -
b1110 1
1$
#460000
0$
#465000
b1111 )
b1111 -
b1111 1
1$
#470000
0$
#475000
b0 )
b0 -
b0 1
1$
#480000
0$
#485000
b1 )
b1 -
b1 1
1$
#490000
0$
#495000
b10 )
b10 -
b10 1
1$
#500000
0$
#505000
0/
1(
b11 )
b11 -
b11 1
1$
#510000
0$
#515000
1!
1$
