aula_(28_e_29)_march/lab1/demux.v
module demux
#(
    parameter WIDTH = 5
)(
    input  wire[1:0]           sel,
    output reg    demux_out0,
    output reg    demux_out1,
    output reg    demux_out2,
    output reg    demux_out3
);

always @(*) begin
    demux_out0 = 0;
    demux_out1 = 0;
    demux_out2 = 0;
    demux_out3 = 0; 
    case (sel)
        2'b11: demux_out3 = 1;
        2'b10: demux_out2 = 1;
        2'b01: demux_out1 = 1;
        2'b00: demux_out0 = 1;
    endcase
end

endmodule

aula_(28_e_29)_march/lab1/mux.v
module mux
#(
    parameter WIDTH = 5
)(
    input wire[WIDTH-1:0]     in0,
    input wire[WIDTH-1:0]     in1,
    input wire[WIDTH-1:0]     in2,
    input wire[WIDTH-1:0]     in3,
    input wire[1:0]           sel,
    output reg[WIDTH-1:0]    mux_out
);

always @(*) begin
    case (sel)
        2'b11: mux_out = in3;
        2'b10: mux_out = in2;
        2'b01: mux_out = in1;
        2'b00: mux_out = in0;
    endcase
end

endmodule

aula_(28_e_29)_march/lab1/encode_priority.v
module encode_priority
(
    input  wire         in0,
    input  wire         in1,
    input  wire         in2,
    input  wire         in3,
    output reg[1:0]    sel
);

always @(*) begin
    if (in3) begin
        sel = 11;
    end else if (in2) begin
        sel = 10;
    end else if (in1) begin
        sel = 01;
    end else begin
        sel = 00;
    end
end

endmodule

aula_(28_e_29)_march/lab1/top.v
module top 
#(
    parameter WIDTH = 5
)
(
    input wire event0,
    input wire event1,
    input wire event2,
    input wire event3,
    input wire [WIDTH-1:0] sensor0_data,
    input wire [WIDTH-1:0] sensor1_data,
    input wire [WIDTH-1:0] sensor2_data,
    input wire [WIDTH-1:0] sensor3_data,
    output wire [WIDTH-1:0] sensor_output,
    output wire [3:0] status_output
);

wire [1:0] select_event;

encode_priority encode_priority_i(
    .in0(event0),
    .in1(event1),
    .in2(event2),
    .in3(event3),
    .sel(select_event)
);


mux mux_i(
    .in0(sensor0_data),
    .in1(sensor1_data),
    .in2(sensor2_data),
    .in3(sensor3_data),
    .sel(select_event),
    .mux_out(sensor_output)
);

demux demux_i(
    .sel(select_event),
    .demux_out0(status_output[0]),
    .demux_out1(status_output[1]),
    .demux_out2(status_output[2]),
    .demux_out3(status_output[3])
);
    
endmodule

aula_(28_e_29)_march/lab1/top_tb.v
module top_tb;


localparam WIDTH = 5;

reg event0;
reg event1;
reg event2;
reg event3;
reg [WIDTH-1:0] sensor0_data;
reg [WIDTH-1:0] sensor1_data;
reg [WIDTH-1:0] sensor2_data;
reg [WIDTH-1:0] sensor3_data;
wire [WIDTH-1:0] sensor_output;
wire [3:0] status_output;


top dut(
    .event0(event0),
    .event1(event1),
    .event2(event2),
    .event3(event3),
    .sensor0_data(sensor0_data),
    .sensor1_data(sensor1_data),
    .sensor2_data(sensor2_data),
    .sensor3_data(sensor3_data),

    .sensor_output(sensor_output),
    .status_output(status_output)
); 

task expect;
    input [4:0] exp_output;
    input [3:0] exp_status;
    if (sensor_output != exp_output || status_output != exp_status ) begin
      $display("\nTEST FAILED");
      $display("event0 = %b, event1 = %b, event2 = %b, event4 = %b", event0,event1,event2,event3);
      $display("sensor0_data = %b, sensor1_data = %b, sensor2_data = %b, sensor4_data = %b", sensor0_data,sensor1_data,sensor2_data,sensor3_data);
      $display("data_out = %b, status_data = %b", sensor_output, status_output);
      $finish;
    end
  endtask

initial 
 begin
    // Testando MUX
  event0 = 0;
  event1 = 1;
  event2 = 0;
  event3 = 0;
  sensor0_data = 5'b10101;
  sensor1_data = 5'b00000;
  sensor2_data = 5'b11111;
  sensor3_data = 5'b01010;
  #1 expect (5'b00000, 4'b0010);
  
  #1;
  event0 = 0;
  event1 = 0;
  event2 = 1;
  event3 = 0;
  sensor0_data = 5'b10101;
  sensor1_data = 5'b00000;
  sensor2_data = 5'b11111;
  sensor3_data = 5'b01010;
  #1 expect (5'b11111, 4'b0100);
  
  #1;
  event0 = 0;
  event1 = 0;
  event2 = 0;
  event3 = 1;
  sensor0_data = 5'b10101;
  sensor1_data = 5'b00000;
  sensor2_data = 5'b11111;
  sensor3_data = 5'b01010;
  #1 expect (5'b01010, 4'b1000);
  
  //TEST DE PRIORIDADE
  event0 = 0;
  event1 = 1;
  event2 = 0;
  event3 = 1;
  sensor0_data = 5'b10101;
  sensor1_data = 5'b00000;
  sensor2_data = 5'b11111;
  sensor3_data = 5'b01010;
  #1 expect (5'b01010, 4'b1000);

  event0 = 1;
  event1 = 1;
  event2 = 1;
  event3 = 0;
  sensor0_data = 5'b10101;
  sensor1_data = 5'b00000;
  sensor2_data = 5'b11111;
  sensor3_data = 5'b01010;
  #1 expect (5'b11111, 4'b0100);



  $finish; // let's stop the simulation here.
 end

 initial begin
  $dumpfile("top_tb.vcd");
  $dumpvars(0, top_tb);
end

endmodule

aula_(28_e_29)_march/lab1/top_tb.vcd
$date
	Sat Mar 28 10:13:27 2026
$end
$version
	Icarus Verilog
$end
$timescale
	1s
$end
$scope module top_tb $end
$var wire 4 ! status_output [3:0] $end
$var wire 5 " sensor_output [4:0] $end
$var parameter 32 # WIDTH $end
$var reg 1 $ event0 $end
$var reg 1 % event1 $end
$var reg 1 & event2 $end
$var reg 1 ' event3 $end
$var reg 5 ( sensor0_data [4:0] $end
$var reg 5 ) sensor1_data [4:0] $end
$var reg 5 * sensor2_data [4:0] $end
$var reg 5 + sensor3_data [4:0] $end
$scope module dut $end
$var wire 1 $ event0 $end
$var wire 1 % event1 $end
$var wire 1 & event2 $end
$var wire 1 ' event3 $end
$var wire 5 , sensor0_data [4:0] $end
$var wire 5 - sensor1_data [4:0] $end
$var wire 5 . sensor2_data [4:0] $end
$var wire 5 / sensor3_data [4:0] $end
$var wire 4 0 status_output [3:0] $end
$var wire 5 1 sensor_output [4:0] $end
$var wire 2 2 select_event [1:0] $end
$var parameter 32 3 WIDTH $end
$scope module demux_i $end
$var wire 2 4 sel [1:0] $end
$var parameter 32 5 WIDTH $end
$var reg 1 6 demux_out0 $end
$var reg 1 7 demux_out1 $end
$var reg 1 8 demux_out2 $end
$var reg 1 9 demux_out3 $end
$upscope $end
$scope module encode_priority_i $end
$var wire 1 $ in0 $end
$var wire 1 % in1 $end
$var wire 1 & in2 $end
$var wire 1 ' in3 $end
$var reg 2 : sel [1:0] $end
$upscope $end
$scope module mux_i $end
$var wire 5 ; in0 [4:0] $end
$var wire 5 < in1 [4:0] $end
$var wire 5 = in2 [4:0] $end
$var wire 5 > in3 [4:0] $end
$var wire 2 ? sel [1:0] $end
$var parameter 32 @ WIDTH $end
$var reg 5 A mux_out [4:0] $end
$upscope $end
$upscope $end
$scope task expect $end
$var reg 5 B exp_output [4:0] $end
$var reg 4 C exp_status [3:0] $end
$upscope $end
$upscope $end
$enddefinitions $end
$comment Show the parameter values. $end
$dumpall
b101 @
b101 5
b101 3
b101 #
$end
#0
$dumpvars
bx C
bx B
b0 A
b1 ?
b1010 >
b11111 =
b0 <
b10101 ;
b1 :
09
08
17
06
b1 4
b1 2
b0 1
b10 0
b1010 /
b11111 .
b0 -
b10101 ,
b1010 +
b11111 *
b0 )
b10101 (
0'
0&
1%
0$
b0 "
b10 !
$end
#1
b10 C
b0 B
#2
b100 !
b100 0
18
07
b11111 "
b11111 1
b11111 A
b10 2
b10 4
b10 :
b10 ?
1&
0%
#3
b100 C
b11111 B
#4
b1000 !
b1000 0
19
08
b1010 "
b1010 1
b1010 A
b11 2
b11 4
b11 :
b11 ?
1'
0&
#5
1%
b1000 C
b1010 B
#6
b100 !
b100 0
18
09
b11111 "
b11111 1
b11111 A
b10 2
b10 4
b10 :
b10 ?
0'
1&
1$
#7
b100 C
b11111 B
