aula_11_09/at4_desenrolado.v
module x3x2x_notFull (clk , x, polinomio , rst );
    parameter lengthX = 8;
    input clk , rst ;
    input [ lengthX -1:0] x;
    output [3* lengthX -1:0] polinomio ;
    reg [15:0] x2;
    reg [3* lengthX -1:0] x3 , pol;

    always @( posedge clk or posedge rst ) begin
        if ( rst ) begin
            x2 <= 0;
            x3 <= 0;
            pol <= 0;
        end
        else begin
            x2 <= x*x;
            x3 <= x2 * x;
            pol <= x3 + x2 + x;
        end
    end
    assign polinomio = pol ;
endmodule

aula_11_09/tb_at4_desenrolado.v
`timescale 1ns/1ps

module tb_at4_desenrolado;
    localparam lengthX = 8;

    reg clk;
    reg rst;
    reg [lengthX-1:0] x;
    wire [3*lengthX-1:0] polinomio;

    integer errors;

    x3x2x_notFull #(.lengthX(lengthX)) dut (
        .clk(clk),
        .x(x),
        .polinomio(polinomio),
        .rst(rst)
    );

    initial clk = 0;
    always #5 clk = ~clk;

    function [3*lengthX-1:0] polynomial;
        input [lengthX-1:0] value;
        begin
            polynomial = (value * value * value) + (value * value) + value;
        end
    endfunction

    task reset_dut;
        begin
            @(negedge clk);
            rst = 1'b1;
            x = 0;
            @(posedge clk);
            #1;

            if (polinomio !== 0) begin
                $error("polinomio deveria zerar no reset, mas vale %0d", polinomio);
                errors = errors + 1;
            end

            @(negedge clk);
            rst = 1'b0;
        end
    endtask

    task run_constant_case;
        input [lengthX-1:0] value;
        reg [3*lengthX-1:0] expected;
        begin
            expected = polynomial(value);

            x = value;
            repeat (4) @(posedge clk);
            #1;

            if (polinomio !== expected) begin
                $error("polinomio=%0d, esperado=%0d para x=%0d",
                       polinomio, expected, value);
                errors = errors + 1;
            end
        end
    endtask

    initial begin
        $dumpfile("tb_at4_desenrolado.vcd");
        $dumpvars(0, tb_at4_desenrolado);

        errors = 0;
        rst = 1'b0;
        x = 0;

        reset_dut();
        run_constant_case(8'd2);
        run_constant_case(8'd3);
        run_constant_case(8'd7);
        run_constant_case(8'd10);

        if (errors == 0)
            $display("tb_at4_desenrolado: PASS");
        else
            $display("tb_at4_desenrolado: FAIL com %0d erro(s)", errors);

        $finish;
    end
endmodule

aula_11_09/tb_at4_desenrolado.vcd
$date
	Fri Sep 11 21:01:29 2026
$end
$version
	Icarus Verilog
$end
$timescale
	1ps
$end
$scope module tb_at4_desenrolado $end
$var wire 24 ! polinomio [23:0] $end
$var parameter 32 " lengthX $end
$var reg 1 # clk $end
$var reg 1 $ rst $end
$var reg 8 % x [7:0] $end
$var integer 32 & errors [31:0] $end
$scope function polynomial $end
$var reg 8 ' value [7:0] $end
$upscope $end
$scope module dut $end
$var wire 1 # clk $end
$var wire 24 ( polinomio [23:0] $end
$var wire 1 $ rst $end
$var wire 8 ) x [7:0] $end
$var parameter 32 * lengthX $end
$var reg 24 + pol [23:0] $end
$var reg 16 , x2 [15:0] $end
$var reg 24 - x3 [23:0] $end
$upscope $end
$scope task reset_dut $end
$upscope $end
$scope task run_constant_case $end
$var reg 24 . expected [23:0] $end
$var reg 8 / value [7:0] $end
$upscope $end
$upscope $end
$enddefinitions $end
$comment Show the parameter values. $end
$dumpall
b1000 *
b1000 "
$end
#0
$dumpvars
bx /
bx .
bx -
bx ,
bx +
b0 )
bx (
bx '
b0 &
b0 %
0$
0#
bx !
$end
#5000
b0 ,
1#
#10000
b0 !
b0 (
b0 +
b0 -
1$
0#
#15000
1#
#20000
b10 %
b10 )
b1110 .
b10 '
b10 /
0$
0#
#25000
b10 !
b10 (
b10 +
b100 ,
1#
#30000
0#
#35000
b110 !
b110 (
b110 +
b1000 -
1#
#40000
0#
#45000
b1110 !
b1110 (
b1110 +
1#
#50000
0#
#55000
1#
#56000
b11 %
b11 )
b100111 .
b11 '
b11 /
#60000
0#
#65000
b1111 !
b1111 (
b1111 +
b1100 -
b1001 ,
1#
#70000
0#
#75000
b11000 !
b11000 (
b11000 +
b11011 -
1#
#80000
0#
#85000
b100111 !
b100111 (
b100111 +
1#
#90000
0#
#95000
1#
#96000
b111 %
b111 )
b110001111 .
b111 '
b111 /
#100000
0#
#105000
b101011 !
b101011 (
b101011 +
b111111 -
b110001 ,
1#
#110000
0#
#115000
b1110111 !
b1110111 (
b1110111 +
b101010111 -
1#
#120000
0#
#125000
b110001111 !
b110001111 (
b110001111 +
1#
#130000
0#
#135000
1#
#136000
b1010 %
b1010 )
b10001010110 .
b1010 '
b1010 /
#140000
0#
#145000
b110010010 !
b110010010 (
b110010010 +
b111101010 -
b1100100 ,
1#
#150000
0#
#155000
b1001011000 !
b1001011000 (
b1001011000 +
b1111101000 -
1#
#160000
0#
#165000
b10001010110 !
b10001010110 (
b10001010110 +
1#
