aula_11_09/at3_desenrolado.v
module x3_curto (
    output reg [7:0] XPower ,
    input [7:0] X,
    input clk
);
reg [7:0] XPower1 , XPower2 ;
reg [7:0] X1 , X2;

always @( posedge clk ) begin
    // Pipeline Stage 1
    X1 <= X;
    XPower1 <= X;
    // Pipeline Stage 2
    X2 <= X1;
    XPower2 <= XPower1 * X1;
    // Pipeline stage 3
    XPower <= XPower2 * X2;
end
endmodule

aula_11_09/tb_at3_desenrolado.v
`timescale 1ns/1ps

module tb_at3_desenrolado;
    reg clk;
    reg [7:0] X;
    wire [7:0] XPower;

    integer errors;
    integer cycle;
    reg [7:0] delay0;
    reg [7:0] delay1;

    x3_curto dut (
        .XPower(XPower),
        .X(X),
        .clk(clk)
    );

    initial clk = 0;
    always #5 clk = ~clk;

    function [7:0] cube8;
        input [7:0] value;
        begin
            cube8 = value * value * value;
        end
    endfunction

    task apply_and_check;
        input [7:0] value;
        begin
            X = value;
            @(posedge clk);
            #1;

            if (cycle >= 2 && XPower !== cube8(delay1)) begin
                $error("XPower=%0d, esperado=%0d para X atrasado=%0d",
                       XPower, cube8(delay1), delay1);
                errors = errors + 1;
            end

            delay1 = delay0;
            delay0 = value;
            cycle = cycle + 1;
        end
    endtask

    initial begin
        $dumpfile("tb_at3_desenrolado.vcd");
        $dumpvars(0, tb_at3_desenrolado);

        errors = 0;
        cycle = 0;
        delay0 = 8'd0;
        delay1 = 8'd0;
        X = 8'd0;

        apply_and_check(8'd1);
        apply_and_check(8'd2);
        apply_and_check(8'd3);
        apply_and_check(8'd6);
        apply_and_check(8'd9);
        apply_and_check(8'd12);

        if (errors == 0)
            $display("tb_at3_desenrolado: PASS");
        else
            $display("tb_at3_desenrolado: FAIL com %0d erro(s)", errors);

        $finish;
    end
endmodule

aula_11_09/tb_at3_desenrolado.vcd
$date
	Fri Sep 11 21:01:29 2026
$end
$version
	Icarus Verilog
$end
$timescale
	1ps
$end
$scope module tb_at3_desenrolado $end
$var wire 8 ! XPower [7:0] $end
$var reg 8 " X [7:0] $end
$var reg 1 # clk $end
$var reg 8 $ delay0 [7:0] $end
$var reg 8 % delay1 [7:0] $end
$var integer 32 & cycle [31:0] $end
$var integer 32 ' errors [31:0] $end
$scope function cube8 $end
$var reg 8 ( value [7:0] $end
$upscope $end
$scope module dut $end
$var wire 8 ) X [7:0] $end
$var wire 1 # clk $end
$var reg 8 * X1 [7:0] $end
$var reg 8 + X2 [7:0] $end
$var reg 8 , XPower [7:0] $end
$var reg 8 - XPower1 [7:0] $end
$var reg 8 . XPower2 [7:0] $end
$upscope $end
$scope task apply_and_check $end
$var reg 8 / value [7:0] $end
$upscope $end
$upscope $end
$enddefinitions $end
$comment Show the parameter values. $end
$dumpall
$end
#0
$dumpvars
b1 /
bx .
bx -
bx ,
bx +
bx *
b1 )
bx (
b0 '
b0 &
b0 %
b0 $
0#
b1 "
bx !
$end
#5000
b1 -
b1 *
1#
#6000
b10 "
b10 )
b10 /
b1 &
b1 $
#10000
0#
#15000
b1 .
b1 +
b10 -
b10 *
1#
#16000
b11 "
b11 )
b11 /
b10 &
b10 $
b1 %
#20000
0#
#25000
b1 !
b1 ,
b100 .
b10 +
b11 -
b11 *
1#
#26000
b110 "
b110 )
b110 /
b11 &
b11 $
b10 %
b1 (
#30000
0#
#35000
b1000 !
b1000 ,
b1001 .
b11 +
b110 -
b110 *
1#
#36000
b1001 "
b1001 )
b1001 /
b100 &
b110 $
b11 %
b10 (
#40000
0#
#45000
b11011 !
b11011 ,
b100100 .
b110 +
b1001 -
b1001 *
1#
#46000
b1100 "
b1100 )
b1100 /
b101 &
b1001 $
b110 %
b11 (
#50000
0#
#55000
b11011000 !
b11011000 ,
b1010001 .
b1001 +
b1100 -
b1100 *
1#
#56000
b110 &
b1100 $
b1001 %
b110 (
