aula_11_09/at1_desenrolado.v
module x3_longo (
    output reg [7:0] XPower ,
    input [7:0] X,
    input clk
);
reg [7:0] X1;

always @( posedge clk ) begin
    // Pipeline Stage 1
    X1 <= X;
    XPower <= X1 * X1 * X1;
end

endmodule

aula_11_09/tb_at1_desenrolado.v
`timescale 1ns/1ps

module tb_at1_desenrolado;
    reg clk;
    reg [7:0] X;
    wire [7:0] XPower;

    integer errors;
    reg [7:0] previous_x;

    x3_longo dut (
        .XPower(XPower),
        .X(X),
        .clk(clk)
    );

    initial clk = 0;
    always #5 clk = ~clk;

    function [7:0] cube8;
        input [7:0] value;
        begin
            cube8 = value * value * value;
        end
    endfunction

    task apply_and_check;
        input [7:0] value;
        begin
            X = value;
            @(posedge clk);
            #1;

            if (XPower !== cube8(previous_x)) begin
                $error("XPower=%0d, esperado=%0d para X anterior=%0d",
                       XPower, cube8(previous_x), previous_x);
                errors = errors + 1;
            end

            previous_x = value;
        end
    endtask

    initial begin
        $dumpfile("tb_at1_desenrolado.vcd");
        $dumpvars(0, tb_at1_desenrolado);

        errors = 0;
        X = 8'd2;

        @(posedge clk);
        #1;
        previous_x = X;

        apply_and_check(8'd3);
        apply_and_check(8'd4);
        apply_and_check(8'd5);
        apply_and_check(8'd10);

        if (errors == 0)
            $display("tb_at1_desenrolado: PASS");
        else
            $display("tb_at1_desenrolado: FAIL com %0d erro(s)", errors);

        $finish;
    end
endmodule

aula_11_09/tb_at1_desenrolado.vcd
$date
	Fri Sep 11 21:01:24 2026
$end
$version
	Icarus Verilog
$end
$timescale
	1ps
$end
$scope module tb_at1_desenrolado $end
$var wire 8 ! XPower [7:0] $end
$var reg 8 " X [7:0] $end
$var reg 1 # clk $end
$var reg 8 $ previous_x [7:0] $end
$var integer 32 % errors [31:0] $end
$scope function cube8 $end
$var reg 8 & value [7:0] $end
$upscope $end
$scope module dut $end
$var wire 8 ' X [7:0] $end
$var wire 1 # clk $end
$var reg 8 ( X1 [7:0] $end
$var reg 8 ) XPower [7:0] $end
$upscope $end
$scope task apply_and_check $end
$var reg 8 * value [7:0] $end
$upscope $end
$upscope $end
$enddefinitions $end
$comment Show the parameter values. $end
$dumpall
$end
#0
$dumpvars
bx *
bx )
bx (
b10 '
bx &
b0 %
bx $
0#
b10 "
bx !
$end
#5000
b10 (
1#
#6000
b11 "
b11 '
b11 *
b10 $
#10000
0#
#15000
b1000 !
b1000 )
b11 (
1#
#16000
b100 "
b100 '
b100 *
b11 $
b10 &
#20000
0#
#25000
b11011 !
b11011 )
b100 (
1#
#26000
b101 "
b101 '
b101 *
b100 $
b11 &
#30000
0#
#35000
b1000000 !
b1000000 )
b101 (
1#
#36000
b1010 "
b1010 '
b1010 *
b101 $
b100 &
#40000
0#
#45000
b1111101 !
b1111101 )
b1010 (
1#
#46000
b1010 $
b101 &
