aula_(09)_may/lab3/rom.v
module rom (
    input  wire        clk,
    input  wire        cs, 
    input  wire [4:0]  addr,
    output reg  [7:0]  data_out
);

    reg [7:0] rom [0:15];

    initial begin
        rom[0]  = 8'd0;
        rom[1]  = 8'd1;
        rom[2]  = 8'd1;
        rom[3]  = 8'd2;
        rom[4]  = 8'd3;
        rom[5]  = 8'd5;
        rom[6]  = 8'd8;
        rom[7]  = 8'd13;
        rom[8]  = 8'd21;
        rom[9]  = 8'd34;
        rom[10] = 8'd55;
        rom[11] = 8'd89;
        rom[12] = 8'd144;
        rom[13] = 8'd233;
        rom[14] = 8'd121;
        rom[15] = 8'd98; 
    end

    always @(posedge clk) begin
        if(cs) begin 
            data_out <= rom[addr];
        end
    end

endmodule

aula_(09)_may/lab2/alu.v
module alu
#(parameter WIDTH = 8)
(
    input wire[WIDTH-1:0] in_a,
    input wire[WIDTH-1:0] in_b,
    input wire[2:0]       opcode,
    output reg[WIDTH-1:0]  alu_out,
    output wire            a_is_zero
);

assign a_is_zero = (in_a == {WIDTH{1'b0}});

always @(*)
begin
    case (opcode)
        3'b000: alu_out = in_a;
        3'b001: alu_out = in_a;
        3'b010: alu_out = (in_a + in_b);
        3'b011: alu_out = (in_a & in_b);
        3'b100: alu_out = (in_a ^ in_b);
        3'b101: alu_out = in_b;
        3'b110: alu_out = in_a;
        3'b111: alu_out = in_a;
    endcase
end


endmodule

aula_(09)_may/lab2/ram_single.v
module ram_single (
    input  wire         clk,
    input  wire         cs,
    input  wire         we,
    input  wire [4:0]   addr,
    input  wire [7:0]  data_in,
    output reg  [7:0]  data_out
);

    reg [7:0] ram [0:31];

    always @(posedge clk) begin
        if(cs) begin 
            if (we) begin
                ram[addr] <= data_in;
                data_out  <= data_in;
            end

            else begin
                data_out <= ram[addr];
            end
        end
    end

    initial begin
        $readme("mem_s_dados.txt",ram);
    end

endmodule

aula_(09)_may/lab3/fsm.v
module fsm (
    input  wire clk,
    input  wire rst,
    input  wire start,
    input  wire inicia_operacao,

    output reg fim,
    output reg op_write
);

    parameter IDLE  = 2'b00;
    parameter EXEC  = 2'b01;
    parameter WRITE = 2'b10;

    reg [1:0] estado_atual;
    reg [1:0] proximo_estado;


    always @(posedge clk or posedge rst) begin
        if (rst)
            estado_atual <= IDLE;
        else
            estado_atual <= proximo_estado;
    end

    always @(*) begin

        proximo_estado = estado_atual;

        fim      = 1'b0;
        op_write = 1'b0;

        case (estado_atual)
            IDLE: begin
                fim = 1'b0;
                if (start && inicia_operacao)
                    proximo_estado = EXEC;
                else
                    proximo_estado = IDLE;
            end
            EXEC: proximo_estado = WRITE;
            WRITE: begin
                op_write = 1'b1;
                fim = 1'b1;
                proximo_estado = IDLE;
            end
            default: begin
                proximo_estado = IDLE;
                fim      = 1'b0;
                op_write = 1'b0;

            end

        endcase
    end

endmodule

aula_(09)_may/lab3/top.v
module top(
    input wire clk,
    input wire inicia_operacao,
    input wire rst,
    input wire [4:0] endereco_ram_in,
    input wire wr_en,
    input wire start,
    input wire cs_ram,
    input wire [7:0] dado_usuario,
    input wire [2:0] operacao_ula,
    input wire [4:0] endereco_rom,
    input wire cs_rom,
    output wire fim,
    output wire [7:0] resultado,
    output wire [7:0] sdado_ram,
    output wire [7:0] result_ula,
    output wire [7:0] sdado_rom
);

    localparam WIDTH=8;

    reg  [3:0] rom_addr;
    wire [7:0] rom_data_out;

    fsm fsm_i (
        .clk(clk),
        .rst(rst),
        .start(start),
        .inicia_operacao(inicia_operacao),
        .fim(fim),
        .op_write(op_write)
    );

    wire wr_en_after = wr_en & !start;

    ram_single RAM_SP (
        .clk(clk),
        .cs(cs_ram),
        .we(wr_en_after),
        .addr(endereco_ram_in),
        .data_in(dado_usuario),
        .data_out(sdado_ram)
    );

    alu #( .WIDTH ( WIDTH ))
    alu_inst
    (
        .opcode    (operacao_ula ),
        .in_a      (sdado_rom ),
        .in_b      (sdado_ram ),
        .alu_out   (result_ula) 
    );

    rom ROM (
        .clk(clk),
        .addr(endereco_rom),
        .cs(cs_rom),
        .data_out(sdado_rom)
    );
    
    reg resultado_ff;

    always @(posedge clk)begin
        if(rst)begin
            resultado_ff = 8'b0;
        end
        else if(op_write) begin 
            resultado_ff = result_ula;
        end
    end

    assign resultado = resultado_ff;
endmodule

aula_(09)_may/lab3/top_tb.v
`timescale 1ns/1ps

module top_tb;

    reg clk;
    reg inicia_operacao;
    reg rst;
    reg [4:0] endereco_ram_in;
    reg wr_en;
    reg start;
    reg cs_ram;
    reg [7:0] dado_usuario;
    reg [2:0] operacao_ula;
    reg [4:0] endereco_rom;
    reg cs_rom;

    wire fim;
    wire [7:0] resultado;
    wire [7:0] sdado_ram;
    wire [7:0] result_ula;
    wire [7:0] sdado_rom;

    top dut (
        .clk(clk),
        .inicia_operacao(inicia_operacao),
        .rst(rst),
        .endereco_ram_in(endereco_ram_in),
        .wr_en(wr_en),
        .start(start),
        .cs_ram(cs_ram),
        .dado_usuario(dado_usuario),
        .operacao_ula(operacao_ula),
        .endereco_rom(endereco_rom),
        .cs_rom(cs_rom),
        .fim(fim),
        .resultado(resultado),
        .sdado_ram(sdado_ram),
        .result_ula(result_ula),
        .sdado_rom(sdado_rom)
    );

    always #5 clk = ~clk;

    initial begin

        clk               = 0;
        rst               = 1;
        inicia_operacao   = 0;
        endereco_ram_in   = 0;
        wr_en             = 0;
        start             = 0;
        cs_ram            = 1;
        dado_usuario      = 0;
        operacao_ula      = 3'b000; 
        endereco_rom      = 0;
        cs_rom            = 1;


        #10;
        rst = 0;
        dado_usuario    = 8'd3;
        #1;
        wr_en           = 1;
        endereco_rom    = 5'd1;
        #14;
        dado_usuario    = 8'd4;
        wr_en = 0;
        #1;
        endereco_ram_in   = 1;
        #1;
        dado_usuario    = 8'd5;
        wr_en           = 1;
        #6;
        wr_en           = 0;
        #10;
        wr_en           = 1;
        endereco_ram_in   = 2;
        endereco_rom   = 06;
        #7;
        wr_en           = 0;
        endereco_ram_in   = 4;
        #3;
        wr_en           = 1;
    
        endereco_rom = 5'd1;


        start = 1;
        inicia_operacao = 1;

        start = 0;
        inicia_operacao = 0;

        #20;
        $finish;
    end

    // Monitor em tempo real
    initial begin
        $monitor("T=%0t | rst=%b | start=%b | RAM=%d | ROM=%d | ULA=%d | RESULT=%d | fim=%b",
                  $time,
                  rst,
                  start,
                  sdado_ram,
                  sdado_rom,
                  result_ula,
                  resultado,
                  fim);
    end

    initial begin
        $dumpfile("wave.vcd");
        $dumpvars(0, top_tb);
    end

endmodule

aula_(09)_may/lab3/wave.vcd
$date
	Sat May  9 20:09:01 2026
$end
$version
	Icarus Verilog
$end
$timescale
	1ps
$end
$scope module top_tb $end
$var wire 8 ! sdado_rom [7:0] $end
$var wire 8 " sdado_ram [7:0] $end
$var wire 8 # resultado [7:0] $end
$var wire 8 $ result_ula [7:0] $end
$var wire 1 % fim $end
$var reg 1 & clk $end
$var reg 1 ' cs_ram $end
$var reg 1 ( cs_rom $end
$var reg 8 ) dado_usuario [7:0] $end
$var reg 5 * endereco_ram_in [4:0] $end
$var reg 5 + endereco_rom [4:0] $end
$var reg 1 , inicia_operacao $end
$var reg 3 - operacao_ula [2:0] $end
$var reg 1 . rst $end
$var reg 1 / start $end
$var reg 1 0 wr_en $end
$scope module dut $end
$var wire 1 & clk $end
$var wire 1 ' cs_ram $end
$var wire 1 ( cs_rom $end
$var wire 8 1 dado_usuario [7:0] $end
$var wire 5 2 endereco_ram_in [4:0] $end
$var wire 5 3 endereco_rom [4:0] $end
$var wire 1 , inicia_operacao $end
$var wire 3 4 operacao_ula [2:0] $end
$var wire 1 . rst $end
$var wire 1 / start $end
$var wire 1 0 wr_en $end
$var wire 1 5 wr_en_after $end
$var wire 8 6 sdado_rom [7:0] $end
$var wire 8 7 sdado_ram [7:0] $end
$var wire 8 8 resultado [7:0] $end
$var wire 8 9 result_ula [7:0] $end
$var wire 1 : op_write $end
$var wire 1 % fim $end
$var parameter 32 ; WIDTH $end
$var reg 1 < resultado_ff $end
$scope module RAM_SP $end
$var wire 5 = addr [4:0] $end
$var wire 1 & clk $end
$var wire 1 ' cs $end
$var wire 8 > data_in [7:0] $end
$var wire 1 5 we $end
$var reg 8 ? data_out [7:0] $end
$upscope $end
$scope module ROM $end
$var wire 5 @ addr [4:0] $end
$var wire 1 & clk $end
$var wire 1 ( cs $end
$var reg 8 A data_out [7:0] $end
$upscope $end
$scope module alu_inst $end
$var wire 8 B in_a [7:0] $end
$var wire 8 C in_b [7:0] $end
$var wire 3 D opcode [2:0] $end
$var wire 1 E a_is_zero $end
$var parameter 32 F WIDTH $end
$var reg 8 G alu_out [7:0] $end
$upscope $end
$scope module fsm_i $end
$var wire 1 & clk $end
$var wire 1 , inicia_operacao $end
$var wire 1 . rst $end
$var wire 1 / start $end
$var parameter 2 H EXEC $end
$var parameter 2 I IDLE $end
$var parameter 2 J WRITE $end
$var reg 2 K estado_atual [1:0] $end
$var reg 1 % fim $end
$var reg 1 : op_write $end
$var reg 2 L proximo_estado [1:0] $end
$upscope $end
$upscope $end
$upscope $end
$enddefinitions $end
$comment Show the parameter values. $end
$dumpall
b10 J
b0 I
b1 H
b1000 F
b1000 ;
$end
#0
$dumpvars
b0 L
b0 K
bx G
xE
b0 D
bx C
bx B
bx A
b0 @
bx ?
b0 >
b0 =
x<
0:
bx 9
b0x 8
bx 7
bx 6
05
b0 4
b0 3
b0 2
b0 1
00
0/
1.
b0 -
0,
b0 +
b0 *
b0 )
1(
1'
0&
0%
bx $
b0x #
bx "
bx !
$end
#5000
b100011 $
b100011 9
b100011 G
b100011 "
b100011 7
b100011 ?
b100011 C
1E
b0 !
b0 6
b0 A
b0 B
b0 #
b0 8
0<
1&
#10000
0&
b11 )
b11 1
b11 >
0.
#11000
15
b1 +
b1 3
b1 @
10
#15000
b100 $
b100 9
b100 G
0E
b1 !
b1 6
b1 A
b1 B
b11 "
b11 7
b11 ?
b11 C
1&
#20000
0&
#25000
05
1&
00
b100 )
b100 1
b100 >
#26000
b1 *
b1 2
b1 =
#27000
15
10
b101 )
b101 1
b101 >
#30000
0&
#33000
05
00
#35000
b100100 $
b100100 9
b100100 G
b100011 "
b100011 7
b100011 ?
b100011 C
1&
#40000
0&
#43000
15
b110 +
b110 3
b110 @
b10 *
b10 2
b10 =
10
#45000
b1101 $
b1101 9
b1101 G
b101 "
b101 7
b101 ?
b101 C
b1000 !
b1000 6
b1000 A
b1000 B
1&
#50000
05
0&
b100 *
b100 2
b100 =
00
#53000
15
0,
0/
b1 +
b1 3
b1 @
10
#55000
b110 $
b110 9
b110 G
b1 !
b1 6
b1 A
b1 B
1&
