aula_(09)_may/lab4/fifo.v
module fifo (

    input wire       clk,
    input wire       rst,
    input wire       push_i,     
    input wire       pop_i,      
    input wire [7:0] data_in,     
    output reg [7:0] data_out,     
    output wire      empty,  
    output wire      full, 
    output reg       error   

);

reg [7:0] mem [0:15];
reg [3:0] wr_ptr;
reg [3:0] rd_ptr;
reg [4:0] count;

assign empty = (count == 0);
assign full  = (count == 16);

always @(posedge clk or posedge rst) begin
    if(rst) begin
        wr_ptr  <= 0;
        rd_ptr  <= 0;
        count   <= 0;
        data_out <= 0;
        error <= 0;
    end

    else begin
        error <= 0;
        if(push_i) begin
            if(full) begin
                error <= 1;
            end
            else begin
                mem[wr_ptr] <= data_in; 
                wr_ptr <= wr_ptr + 1;
                count <= count + 1;
            end
        end
        
        if(pop_i) begin
            if(empty) begin
                error <= 1;
            end
            else begin
                data_out <= mem[rd_ptr];
                rd_ptr <= rd_ptr + 1;
                count <= count - 1;
            end
        end

    end
end

endmodule

aula_(09)_may/lab4/tb_fifo.v
`timescale 1ns/1ps

module tb_fifo;


reg clk;
reg rst;
reg push_i;
reg pop_i;
reg [7:0] data_in;
wire [7:0] data_out;
wire empty;
wire full;
wire error;

fifo dut (   
    .clk(clk),   
    .rst(rst),  
    .push_i(push_i),  
    .pop_i(pop_i),  
    .data_in(data_in),
    .data_out(data_out),  
    .empty(empty),  
    .full(full),  
    .error(error)
);

always #5 clk = ~clk;

initial begin
    $dumpfile("fifo_tb.vcd");
    $dumpvars(0, tb_fifo);

    clk = 0;
    rst = 1;
    push_i = 0;
    pop_i = 0;
    data_in = 0;

    #20;
    rst = 0;

    $display("==========================================");
    $display(" TESTE");
    $display("==========================================");

    $display("Tempo\tWR\tRD\tDIN\tDOUT\tEMPTY\tFULL\tERROR");

    $monitor("%0t\t%b\t%b\t%0d\t%0d\t%b\t%b\t%b",
             $time,
             push_i,
             pop_i,
             data_in,
             data_out,
             empty,
             full,
             error);

    $display("\n--- TESTE EMPTY ---");

    #10;
    pop_i = 1;

    #10;
    pop_i = 0;

    $display("\n--- TESTE ESCRITA ---");

    #10;

    push_i = 1;
    data_in = 8'd00; #10;
    data_in = 8'd01; #10;
    data_in = 8'd02; #10;
    data_in = 8'd04; #10;

    push_i = 0;

    $display("\n--- TESTE LEITURA ---");

    #10;
    pop_i = 1;

    #40;
    pop_i = 0;

    $display("\n--- TESTE signal FULL ---");

    #10;

    push_i = 1;
    data_in = 8'd1;  #10;
    data_in = 8'd2;  #10;
    data_in = 8'd3;  #10;
    data_in = 8'd4;  #10;
    data_in = 8'd5;  #10;
    data_in = 8'd6;  #10;
    data_in = 8'd7;  #10;
    data_in = 8'd8;  #10;
    data_in = 8'd9;  #10;
    data_in = 8'd10; #10;
    data_in = 8'd11; #10;
    data_in = 8'd12; #10;
    data_in = 8'd13; #10;
    data_in = 8'd14; #10;
    data_in = 8'd15; #10;
    data_in = 8'd16; #10;

    push_i = 0;

    $display(" FIM DA SIMULACAO ");

    $finish;

end

endmodule

aula_(09)_may/lab4/fifo_tb.vcd
$date
	Sun May 10 21:23:54 2026
$end
$version
	Icarus Verilog
$end
$timescale
	1ps
$end
$scope module tb_fifo $end
$var wire 1 ! full $end
$var wire 1 " error $end
$var wire 1 # empty $end
$var wire 8 $ data_out [7:0] $end
$var reg 1 % clk $end
$var reg 8 & data_in [7:0] $end
$var reg 1 ' pop_i $end
$var reg 1 ( push_i $end
$var reg 1 ) rst $end
$scope module dut $end
$var wire 1 % clk $end
$var wire 8 * data_in [7:0] $end
$var wire 1 ' pop_i $end
$var wire 1 ( push_i $end
$var wire 1 ) rst $end
$var wire 1 ! full $end
$var wire 1 # empty $end
$var reg 5 + count [4:0] $end
$var reg 8 , data_out [7:0] $end
$var reg 1 " error $end
$var reg 4 - rd_ptr [3:0] $end
$var reg 4 . wr_ptr [3:0] $end
$upscope $end
$upscope $end
$enddefinitions $end
$comment Show the parameter values. $end
$dumpall
$end
#0
$dumpvars
b0 .
b0 -
b0 ,
b0 +
b0 *
1)
0(
0'
b0 &
0%
b0 $
1#
0"
0!
$end
#5000
1%
#10000
0%
#15000
1%
#20000
0%
0)
#25000
1%
#30000
0%
1'
#35000
1"
1%
#40000
0%
0'
#45000
0"
1%
#50000
0%
1(
#55000
0#
b1 +
b1 .
1%
#60000
0%
b1 &
b1 *
#65000
b10 +
b10 .
1%
#70000
0%
b10 &
b10 *
#75000
b11 +
b11 .
1%
#80000
0%
b100 &
b100 *
#85000
b100 +
b100 .
1%
#90000
0%
0(
#95000
1%
#100000
0%
1'
#105000
b11 +
b1 -
1%
#110000
0%
#115000
b10 +
b10 -
b1 $
b1 ,
1%
#120000
0%
#125000
b1 +
b11 -
b10 $
b10 ,
1%
#130000
0%
#135000
1#
b0 +
b100 -
b100 $
b100 ,
1%
#140000
0%
0'
#145000
1%
#150000
0%
b1 &
b1 *
1(
#155000
0#
b1 +
b101 .
1%
#160000
0%
b10 &
b10 *
#165000
b10 +
b110 .
1%
#170000
0%
b11 &
b11 *
#175000
b11 +
b111 .
1%
#180000
0%
b100 &
b100 *
#185000
b100 +
b1000 .
1%
#190000
0%
b101 &
b101 *
#195000
b101 +
b1001 .
1%
#200000
0%
b110 &
b110 *
#205000
b110 +
b1010 .
1%
#210000
0%
b111 &
b111 *
#215000
b111 +
b1011 .
1%
#220000
0%
b1000 &
b1000 *
#225000
b1000 +
b1100 .
1%
#230000
0%
b1001 &
b1001 *
#235000
b1001 +
b1101 .
1%
#240000
0%
b1010 &
b1010 *
#245000
b1010 +
b1110 .
1%
#250000
0%
b1011 &
b1011 *
#255000
b1011 +
b1111 .
1%
#260000
0%
b1100 &
b1100 *
#265000
b1100 +
b0 .
1%
#270000
0%
b1101 &
b1101 *
#275000
b1101 +
b1 .
1%
#280000
0%
b1110 &
b1110 *
#285000
b1110 +
b10 .
1%
#290000
0%
b1111 &
b1111 *
#295000
b1111 +
b11 .
1%
#300000
0%
b10000 &
b10000 *
#305000
1!
b10000 +
b100 .
1%
#310000
0%
0(
